{"paths":{"0":["Sprites/dice/xucxac/Thuong_37",1],"1":["Font/font_time_gold-export",1],"2":["TX/xx5_2",1],"3":["TX/tx/bg_timeTX",1],"4":["TX/tx/fan",1],"5":["Sprites/dice/nuttx/xx5_3",1],"6":["TX/tx_ico_tai_fx",1],"7":["TX/UI/luatCHoiTaiXiu",1],"8":["Sprites/bat",1],"9":["TX/tx_bat",1],"10":["TX/tx_nan_btn_active",1],"11":["Spine/jackpot/Group 3173",1],"12":["Sprites/dice/nuttx/xx4_2",1],"13":["TX/UI/btnTrang",1],"14":["TX/UI/btnXingau3Unsellect",1],"15":["Sprites/dice/xucxac/Thuong_5",1],"16":["TX/font/128_timecuoc/fontnumber-export",1],"17":["Sprites/next_phai",1],"18":["tx1/lb_mail_bg",1],"19":["tx1/bt_page_prev_2",1],"20":["Sprites/82_xingauA2/xingauA2",1],"21":["Sprites/ic_guide",1],"22":["TX/ico_kq_tai",1],"23":["Sprites/dice/nuttx/xx3_3",1],"24":["Sprites/dice/xucxac/Thuong_6",1],"25":["TX/32_font_chu_vang/font_chu_vang",1],"26":["TX/animation/98_TX JP/TX JP",1],"27":["Sprites/frame3",1],"28":["TX/tx_3_bridge",1],"29":["Sprites/dice/nuttx/dice_5",1],"30":["TX/tx_xanh2",1],"31":["Sprites/dice/nuttx/xx4_1",1],"32":["Sprites/huong_dan_tx",1],"33":["tx1/10_font_title/font_title",1],"34":["Sprites/dice/xucxac/Thuong_25",1],"35":["Sprites/ic_arrow",1],"36":["TX/bkg-btn_white",1],"37":["Sprites/85_TXspine2/TXspine2",1],"38":["TX/tx/nan",1],"39":["tx1/43_font_money/font_money",1],"40":["tx1/ig_bg_text_2",1],"41":["Sprites/dice/nuttx/xx3_2",1],"42":["tx1/lb_popup_title_bg_1",1],"43":["Sprites/dice/xucxac/Thuong_44",1],"44":["Spine/title/taixiu",1],"45":["Sprites/dice/nuttx/xx6_3",1],"46":["TX/UI/Icon_Tick",1],"47":["TX/tx/vong_tien",1],"48":["TX/UI/boderCopy",1],"49":["tx1/btn_2",1],"50":["Sprites/dice/xucxac/Thuong_10",1],"51":["tx1/lb_khung_ten",1],"52":["TX/UI/iconBackTron1",1],"53":["tx1/btn_check_2",1],"54":["Sprites/BIG",1],"55":["Sprites/dice/xucxac/Thuong_39",1],"56":["Sprites/dice/xucxac/Thuong_3",1],"57":["Sprites/dice/xucxac/Thuong_17",1],"58":["tx1/btn_tab_0",1],"59":["Sprites/dice/nuttx/dice_6",1],"60":["TX/tx_ico_user_online",1],"61":["Sprites/85_TXspine2/TXspine2",7],"62":["Sprites/dice/nuttx/xx1_2",1],"63":["TX/UI/tab_duatop_taixiu_off",1],"64":["Sprites/dice/82_xingauA2/xingauA2",7],"65":["Sounds/click",5],"66":["TX/UI/icoNext",1],"67":["TX/tx/btn_putmoney",1],"68":["Sprites/dice/nuttx/dice_4",1],"69":["TX/tx_xanh",1],"70":["TX/24_font_count_down/font_count_down",1],"71":["TX/46_haitac_font_money/haitac_font_money",1],"72":["Sprites/dice/xucxac/Thuong_20",1],"73":["TX/tx/btn_closegame_s",1],"74":["Spine/taixiuText/taixiu",7],"75":["Sprites/SMALL",1],"76":["tx1/btn_check_1",1],"77":["Sprites/dice/xucxac/Thuong_32",1],"78":["Sprites/dice/xucxac/Thuong_26",1],"79":["Sprites/dice/xucxac/Thuong_22",1],"80":["TX/tx/tele)",1],"81":["tx1/btn_check_3",1],"82":["TX/UI/Panel_ThongKe",1],"83":["Sprites/fixtaixiu/ani-xoay/ho",7],"84":["Sprites/jp_small",1],"85":["Sprites/fixtaixiu/ani-win/fx",7],"86":["TX/tx_input_money_light_tai",1],"87":["TX/UI/Icon_Rank_No2",1],"88":["Sprites/dice/nuttx/xx1_1",1],"89":["TX/tx_bg_qtdb",1],"90":["Sprites/dice/skeleton4",1],"91":["TX/tx/vong_den",1],"92":["TX/tx/splash",1],"93":["tx1/tx_1",1],"94":["TX/font/25_fonJackpotIdMember-export/fonJackpotIdMember-export",1],"95":["Sprites/dice/skeleton2",1],"96":["Sprites/dice/skeleton",7],"97":["TX/UI/lineNgang",1],"98":["TX/tx/userTX",1],"99":["TX/tx/PlistMNTaiXiu (1)",1],"100":["Sprites/dice/xucxac/Thuong_29",1],"101":["Sprites/dice/xucxac/Thuong_2",1],"102":["Sprites/hu_tai",1],"103":["TX/50_font_money/font_money",1],"104":["Sprites/hu_xiu",1],"105":["TX/UI/btnXingau3",1],"106":["Sounds/Tieng-click-chuot-www_tiengdong_com (1)",5],"107":["TX/btn_1",1],"108":["Sprites/dice/xucxac/Thuong_34",1],"109":["TX/tx/chat",1],"110":["Sounds/ES_Dice Roll 2",5],"111":["Sprites/data_1",1],"112":["TX/tx_bgresult_xiu",1],"113":["TX/tx_1_bridge",1],"114":["Sprites/dice/nuttx/xx3_1",1],"115":["Sprites/bgz",1],"116":["Sprites/bg",1],"117":["Sprites/dice/nuttx/dice_3",1],"118":["TX/tx/PlistMNTaiXiu",1],"119":["Sprites/dice/skeleton7",1],"120":["Spine/title/title_taixiu/taixiu",1],"121":["Sounds/Winer",5],"122":["TX/ig_bg_text_3",1],"123":["Sprites/jb_big",1],"124":["TX/tx/nv)",1],"125":["tx1/btn_tab_1",1],"126":["Sprites/dice/xucxac/Thuong_7",1],"127":["TX/btn_2",1],"128":["tx1/21_font_text_lobby/font_text_lobby",1],"129":["TX/tx_input_money_light_xiu",1],"130":["tx1/pane",1],"131":["Sprites/dice/xucxac/Thuong_11",1],"132":["Sprites/btn_100",1],"133":["Spine/83_effect/effect",1],"134":["TX/tx/bg_chat_new",1],"135":["Sprites/dice/xucxac/Thuong_28",1],"136":["Sprites/dice/xucxac/Thuong_36",1],"137":["TX/tx_bg_songuoichoi_tai",1],"138":["TX/tx_doc",1],"139":["tx1/tx_bgresult_xiu",1],"140":["Sprites/vongxoay",1],"141":["tx1/lb_edit_box",1],"142":["TX/tx_2",1],"143":["TX/UI/hangBoder",1],"144":["TX/xx2_2",1],"145":["TX/f",1],"146":["TX/animation/85_TXspine2/TXspine2",7],"147":["tx1/btn_check_1_2",1],"148":["Spine/AnimVongXoay/taixiu",1],"149":["Sprites/dice/xucxac/Thuong_8",1],"150":["Sprites/line",1],"151":["TX/UI/Icon_Rank_No1",1],"152":["Sprites/dice/xucxac/Thuong_33",1],"153":["tx1/tut_tx",1],"154":["TX/UI/Icon_Rank_No3",1],"155":["TX/tx/bg_vongtron",1],"156":["TX/tx_nan_btn_inactive",1],"157":["TX/xx1_2",1],"158":["TX/xx4_2",1],"159":["Sprites/dice/xucxac/Thuong_24",1],"160":["TX/UI/btnXingau1",1],"161":["TX/UI/btnXingau1Unsellect",1],"162":["TX/UI/btnXingau2Unsellect",1],"163":["TX/tx/bat_nan3",1],"164":["TX/UI/data_2",1],"165":["TX/tx_bg_lightqt",1],"166":["tx1/popup",1],"167":["TX/ig_bg_thong_bao",1],"168":["TX/tx_bg_chat",1],"169":["Sprites/roll",1],"170":["Sprites/data_2",1],"171":["TX/UI/line_yellow",1],"172":["Sprites/dice/nuttx/xx1_3",1],"173":["tx1/tx_table_bg",1],"174":["TX/tx/tai1",1],"175":["TX/tx_btn_soicau",1],"176":["Sprites/dice/xucxac/Thuong_12",1],"177":["TX/xx6_2",1],"178":["TX/tx_input_money_xiu",1],"179":["Spine/taixiuText/taixiutext",1],"180":["tx1/title_thongtin",1],"181":["TX/tx/sp_tai",1],"182":["TX/UI/icon_reward_duatop_0",1],"183":["TX/tx_ico_xiu_fx",1],"184":["tx1/bt_page_next_2",1],"185":["Sprites/next_trai",1],"186":["TX/UI/icoBack",1],"187":["Sprites/toast",1],"188":["TX/tx_4",1],"189":["TX/tx_btn_history",1],"190":["Sprites/dice/skeleton8",1],"191":["TX/tx/gif",1],"192":["Sprites/dice/xucxac/Thuong_14",1],"193":["Sprites/dice/xucxac/Thuong_30",1],"194":["TX/xiu_default",1],"195":["TX/tx/bonan",1],"196":["Sprites/dice/xucxac/Thuong_21",1],"197":["TX/tx/btn_send_chat",1],"198":["TX/tx_btn_thongke",1],"199":["TX/tx/bg_soicau",1],"200":["tx1/bg_progress",1],"201":["Sprites/dice/skeleton9",1],"202":["TX/tx_bg",1],"203":["Sprites/huong_dan_tx_en",1],"204":["Sprites/dice/xucxac/Thuong_41",1],"205":["Sprites/dice/xucxac/Thuong_4",1],"206":["TX/tx_btn_bet",1],"207":["Spine/title/title_taixiu/taixiu",7],"208":["Sprites/dice/nuttx/dice_2",1],"209":["TX/UI/board_history",1],"210":["Sprites/dice/xucxac/Thuong_38",1],"211":["TX/UI/Frame_Notification_1",1],"212":["TX/tx_win_money_bg",1],"213":["TX/tai_default",1],"214":["Sprites/btn_50m",1],"215":["Sprites/dice/xucxac/Thuong_16",1],"216":["Sprites/font/font-export",1],"217":["tx1/btn_back",1],"218":["TX/font/65_SFUEurostileDemiStroke/SFUEurostileDemiStroke",1],"219":["TX/tx/btn_quit",1],"220":["Sprites/dice/xucxac/Thuong_31",1],"221":["TX/tx_btn_close",1],"222":["TX/UI/lineLSP",1],"223":["Sprites/dice/nuttx/xx5_2",1],"224":["Sprites/dice/xucxac/Thuong_35",1],"225":["Sprites/dice/xucxac/Thuong_40",1],"226":["Sprites/dice/dices-2",1],"227":["TX/tx_bkg_bet_input_xiu",1],"228":["tx1/btn_1",1],"229":["TX/tx/sp_xiu",1],"230":["Sprites/dice/xucxac/Thuong_19",1],"231":["Sprites/dice/nuttx/xx2_3",1],"232":["TX/UI/bg",1],"233":["Sprites/dice/skeleton6",1],"234":["TX/4_font_chu_do/font_chu_do",1],"235":["TX/tx/bangvinhdanh",1],"236":["TX/icon_thongbao",1],"237":["tx1/btn_check_2_2",1],"238":["Sprites/taixiu_canbang",1],"239":["TX/UI/tab_duatop_off",1],"240":["TX/tx/otp",1],"241":["Sprites/dice/xucxac/Thuong_42",1],"242":["tx1/tx_bg_chat",1],"243":["TX/UI/tab_duatop_taixiu_on",1],"244":["tx1/ico_kq_tai",1],"245":["TX/UI/lineNgang2",1],"246":["Sprites/dice/xucxac/Thuong_27",1],"247":["TX/font/113_MyriadB_Gold-export/MyriadB_Gold-export",1],"248":["tx1/panel_all",1],"249":["TX/UI/data_1",1],"250":["TX/ico_kq_xiu",1],"251":["TX/tx_btn_close_chat",1],"252":["TX/31_font_chu_tim/font_chu_tim",1],"253":["TX/UI/tab_duatop_on",1],"254":["Spine/AnimVongXoay/taixiu",7],"255":["tx1/lb_icon_rank_1",1],"256":["tx1/lb_icon_rank_3",1],"257":["TX/UI/tableNap",1],"258":["TX/tx_btn_chat",1],"259":["TX/tx/txchon",1],"260":["TX/tx_2_bridge",1],"261":["Sprites/dice/nuttx/xx6_1",1],"262":["tx1/tx_bgresult_tai",1],"263":["TX/font/119_thantai_roboto_bold_40_2/thantai_roboto_bold_40_2",1],"264":["TX/xiu_on",1],"265":["Spine/taixiuText/taixiu",1],"266":["Sprites/dot_black",1],"267":["Sprites/dice/nuttx/xx2_2",1],"268":["Sprites/dice/nuttx/dice_1",1],"269":["tx1/ct_btn_play",1],"270":["tx1/tx_3",1],"271":["Sprites/dice/xucxac/Thuong_9",1],"272":["tx1/bg_mode_picker",1],"273":["Sprites/dice/xucxac/Thuong_13",1],"274":["TX/UI/btnXingau2",1],"275":["tx1/btn_check_3_2",1],"276":["Sprites/dot_white",1],"277":["TX/tx/lsgd",1],"278":["TX/tx_current_money_xiu",1],"279":["TX/UI/line",1],"280":["TX/tx/huongdan",1],"281":["TX/tx_btn_rank",1],"282":["tx1/4_font_chu_do/font_chu_do",1],"283":["TX/tx_4_bridge",1],"284":["TX/tx_bkg_bet_input_tai",1],"285":["TX/tx_3",1],"286":["tx1/lb_icon_bank_blank",1],"287":["Sprites/dice/xucxac/hinhcuoi_vitri",1],"288":["TX/tx/btn_putmoney2",1],"289":["Sprites/dice/nuttx/xx4_3",1],"290":["tx1/lb_icon_rank_2",1],"291":["TX/animation/85_TXspine2/TXspine2",1],"292":["TX/UI/lineBoder2",1],"293":["Sprites/fixtaixiu/pack-tx",1],"294":["Sprites/dice/xucxac/Thuong_43",1],"295":["tx1/ico_kq_xiu",1],"296":["tx1/tx_2",1],"297":["TX/UI/Panel_ThongKe_2",1],"298":["TX/tx/btn_soicau_s",1],"299":["Sounds/clockTick",5],"300":["TX/tx_bgresult_tai",1],"301":["tx1/btn_3",1],"302":["TX/23_font_money_2/font_money_2",1],"303":["Sprites/dice/nuttx/xx6_2",1],"304":["TX/UI/ghiSoDe",1],"305":["TX/tx_den",1],"306":["tx1/tx_4",1],"307":["Spine/jackpot/nohu_taixiu",1],"308":["TX/tx_1",1],"309":["Sprites/fixtaixiu/ani-xoay/ho",1],"310":["TX/animation/98_TX JP/TX JP",7],"311":["Sprites/bgs",1],"312":["Sprites/dice/skeleton3",1],"313":["TX/tx_bg_jackpot",1],"314":["Sprites/dice/skeleton5",1],"315":["Sprites/btn_500",1],"316":["TX/tx_text_game",1],"317":["Sprites/dice/xucxac/Thuong_18",1],"318":["Sprites/dice/nuttx/xx5_1",1],"319":["Font/SVN-Hemi_Head",0],"320":["Sprites/82_xingauA2/xingauA2",7],"321":["TX/66_thantai_text_game/thantai_text_game",1],"322":["Sprites/dice/skeleton",1],"323":["TX/tx_input_money_tai",1],"324":["TX/tx/foot",1],"325":["Sprites/dice/xucxac/Thuong_23",1],"326":["Spine/83_effect/effect",7],"327":["Font/font_time_red-export",1],"328":["TX/tx/ev",1],"329":["TX/tx_current_money_tai",1],"330":["TX/font/111_ArialB_W-export/ArialB_W-export",1],"331":["Sprites/bgsc",1],"332":["TX/xx3_2",1],"333":["TX/tx_btn_support",1],"334":["TX/UI/lineBoder3",1],"335":["Sprites/dice/xucxac/Thuong_45",1],"336":["Sprites/dice/nuttx/xx2_1",1],"337":["Sprites/dice/xucxac/Thuong_1",1],"338":["TX/tai_on",1],"339":["TX/tx/txtXiu",1],"340":["Sprites/dice/82_xingauA2/xingauA2",1],"341":["Spine/title/taixiu",7],"342":["Spine/jackpot/nohu_taixiu",7],"343":["Sprites/fixtaixiu/ani-win/fx",1],"344":["Sprites/dice/xucxac/Thuong_15",1],"345":["TX/UI/table",1],"346":["TX/font/95_HelveticaNeue_W-export/HelveticaNeue_W-export",1],"347":["Sprites/dice/skeleton10",1],"348":["Spine/title/taixiu.atlas",8],"349":["TX/tx_nan_btn_active",3,1],"350":["tx1/btn_check_3_2",3,1],"351":["TX/UI/btnXingau2",3,1],"352":["TX/tx/btn_quit",3,1],"353":["Sprites/hu_xiu",3,1],"354":["TX/UI/borderTable",3,1],"355":["Sprites/dice/xucxac/Thuong_30",3,1],"356":["TX/tx/huongdan",3,1],"357":["Sprites/dice/skeleton3",3,1],"358":["Sprites/dice/nuttx/dice_3",3,1],"359":["TX/font/60_Font-export/Font-export",3,1],"360":["tx1/btn_close",3,1],"361":["Sprites/fixtaixiu/ani-xoay/ho",3,1],"362":["Sprites/dice/xucxac/Thuong_29",3,1],"363":["TX/tx_bg_songuoichoi_tai",3,1],"364":["Sprites/dice/xucxac/Thuong_45",3,1],"365":["Sprites/dice/nuttx/dice_5",3,1],"366":["tx1/lb_icon_bank_blank",3,1],"367":["tx1/tx_3",3,1],"368":["Sprites/dice/xucxac/Thuong_18",3,1],"369":["TX/font/95_HelveticaNeue_W-export/HelveticaNeue_W-export",2],"370":["Sprites/frame3",3,1],"371":["tx1/bg_mode_picker",3,1],"372":["TX/4_font_chu_do/font_chu_do",2],"373":["Spine/taixiuText/taixiu",3,1],"374":["TX/tx_input_money_light_tai",3,1],"375":["Popup/PopupGuide",4],"376":["TX/46_haitac_font_money/haitac_font_money",3,1],"377":["TX/tx_2",3,1],"378":["TX/UI/Icon_Tick",3,1],"379":["TX/UI/btnXingau3Unsellect",3,1],"380":["TX/ig_bg_text_3",3,1],"381":["TX/tx_3",3,1],"382":["TX/tx_ico_xiu_fx",3,1],"383":["TX/UI/tab_duatop_off",3,1],"384":["TX/tx_btn_bet",3,1],"385":["TX/tx/splash",3,1],"386":["fxDice",10],"387":["tx1/31_font_chu_tim/font_chu_tim",2],"388":["TX/tx_bgresult_tai",3,1],"389":["tx1/31_font_chu_tim/font_chu_tim",3,1],"390":["TX/tx/btn_putmoney",3,1],"391":["TX/UI/AslatTX",9],"392":["tx1/ico_kq_xiu",3,1],"394":["TX/UI/ghiSoDe",3,1],"395":["TX/tx_nan_btn_inactive",3,1],"396":["tx1/5_font_chu_vang/font_chu_vang",1],"397":["TX/font/119_thantai_roboto_bold_40_2/thantai_roboto_bold_40_2",3,1],"398":["TX/xx6_2",3,1],"399":["TX/UI/table",3,1],"400":["TX/tai_default",3,1],"401":["TX/31_font_chu_tim/font_chu_tim",3,1],"402":["TX/tx_input_money_tai",3,1],"403":["Font/font_time_gold-export",2],"404":["Sprites/ic_arrow",3,1],"405":["TX/UI/Frame_Notification_1",3,1],"406":["TX/tx_xanh2",3,1],"407":["TX/UI/line_yellow",3,1],"408":["Popup/PopupHonors",4],"409":["TX/32_font_chu_vang/font_chu_vang",2],"410":["tx1/21_font_text_lobby/font_text_lobby",2],"411":["Sprites/jb_big",3,1],"412":["tx1/popup",3,1],"413":["Sprites/SMALL",3,1],"414":["TX/xx5_2",3,1],"415":["Sprites/font/font-export",2],"416":["tx1/tx_bgresult_xiu",3,1],"417":["Sprites/dice/xucxac/Thuong_11",3,1],"418":["TX/font/111_ArialB_W-export/ArialB_W-export",2],"419":["TX/UI/data_2",3,1],"420":["tx1/10_font_title/font_title",2],"421":["Sprites/dice/xucxac/Thuong_27",3,1],"422":["Sprites/dice/nuttx/xx4_2",3,1],"423":["tx1/popup_1",3,1],"424":["TX/UI/icoBack",3,1],"425":["TX/31_font_chu_tim/font_chu_tim",2],"426":["tx1/tx_bg_chat",3,1],"427":["Spine/83_effect/effect",6],"428":["Sprites/dice/nuttx/xx2_3",3,1],"429":["Sprites/dice/82_xingauA2/xingauA2",6],"430":["tx1/btn_close",1],"431":["tx1/tx_bgresult_tai",3,1],"432":["Sprites/dice/xucxac/Thuong_12",3,1],"433":["TX/font/111_ArialB_W-export/ArialB_W-export",3,1],"434":["tx1/btn_check_2_2",3,1],"435":["Spine/jackpot/nohu_taixiu",3,1],"436":["Sprites/fixtaixiu/ani-xoay/ho",6],"437":["TX/font/113_MyriadB_Gold-export/MyriadB_Gold-export",3,1],"438":["Spine/AnimVongXoay/taixiu",3,1],"439":["Sprites/dice/xucxac/Thuong_2",3,1],"440":["tx1/btn_1",3,1],"441":["TX/UI/boderCopy",3,1],"442":["tx1/bt_page_next_2",3,1],"443":["Sprites/dice/xucxac/Thuong_15",3,1],"444":["tx1/lb_icon_rank_1",3,1],"445":["TX/tx/bg_vongtron",3,1],"446":["tx1/ig_bg_text_2",3,1],"447":["TX/animation/85_TXspine2/TXspine2",3,1],"448":["Sprites/dice/nuttx/xx5_1",3,1],"449":["Popup/PopupSoiCau",4],"450":["Sprites/dice/nuttx/xx5_2",3,1],"451":["TX/23_font_money_2/font_money_2",3,1],"452":["tx1/lb_edit_box",3,1],"453":["tx1/48_font_chu_vang/font_chu_vang",1],"454":["TX/tx_bat",3,1],"455":["Sprites/dice/nuttx/xx4_1",3,1],"456":["Spine/jackpot/nohu_taixiu",6],"457":["Sprites/ic_guide",3,1],"458":["Sprites/dice/xucxac/Thuong_36",3,1],"459":["TX/66_thantai_text_game/thantai_text_game",3,1],"460":["TX/tx/PlistMNTaiXiu",3,1],"461":["Spine/taixiuText/taixiutext",6],"462":["tx1/tx_1",3,1],"463":["tx1/5_font_chu_vang/font_chu_vang",2],"464":["TX/tx_input_money_light_xiu",3,1],"465":["TX/font/65_SFUEurostileDemiStroke/SFUEurostileDemiStroke",2],"466":["TX/tx_btn_history",3,1],"467":["Sprites/BIG",3,1],"468":["TX/tx_4",3,1],"469":["Spine/83_effect/effect",3,1],"470":["TX/tx_2_bridge",3,1],"471":["TX/xx3_2",3,1],"472":["TX/tx_btn_close_chat",3,1],"473":["Sprites/dice/skeleton4",3,1],"474":["Sprites/dice/skeleton6",3,1],"475":["TX/UI/data_1",3,1],"476":["TX/tx/tele)",3,1],"477":["Sprites/dice/xucxac/Thuong_32",3,1],"478":["Sprites/font/font-export",3,1],"479":["Sprites/dice/xucxac/Thuong_24",3,1],"480":["Sprites/dice/nuttx/xx6_3",3,1],"481":["TX/UI/luatCHoiTaiXiu",3,1],"482":["Sprites/dice/xucxac/Thuong_26",3,1],"483":["Sprites/hu_tai",3,1],"484":["TX/tx_bg",3,1],"485":["Sprites/dice/nuttx/xx3_3",3,1],"486":["TX/font/95_HelveticaNeue_W-export/HelveticaNeue_W-export",3,1],"487":["TX/4_font_chu_do/font_chu_do",3,1],"488":["TX/xiu_default",3,1],"489":["Font/font_time_red-export",3,1],"490":["TX/tx/ev",3,1],"491":["Sprites/dice/xucxac/Thuong_23",3,1],"492":["Sprites/dice/xucxac/Thuong_35",3,1],"493":["tx1/btn_tab_0",3,1],"494":["TX/font/101_MyriadSemiB_YWY-export/MyriadSemiB_YWY-export",1],"495":["TX/tx_btn_chat",3,1],"496":["TX/UI/line",3,1],"497":["Sprites/dice/skeleton2",3,1],"498":["Spine/title/taixiu",6],"499":["TaiXiuDouble",4],"500":["TX/ico_kq_tai",3,1],"501":["TX/tx/tai1",3,1],"502":["Sprites/btn_500",3,1],"503":["Sprites/dot_black",3,1],"504":["TX/UI/AslatTX",1],"505":["Sprites/bat",3,1],"506":["Sprites/toast",3,1],"507":["Sprites/dice/nuttx/xx1_2",3,1],"508":["Sprites/roll",3,1],"509":["TX/UI/btnXingau1Unsellect",3,1],"510":["tx1/4_font_chu_do/font_chu_do",2],"511":["tx1/popup_1",1],"512":["TX/xx2_2",3,1],"513":["TX/font/128_timecuoc/fontnumber-export",2],"514":["TX/tx_current_money_tai",3,1],"515":["TX/tx_xanh",3,1],"516":["Sprites/dice/xucxac/Thuong_10",3,1],"517":["tx1/bg_progress",3,1],"518":["TX/tx_1",3,1],"519":["Sprites/82_xingauA2/xingauA2",6],"520":["Sprites/85_TXspine2/TXspine2",3,1],"521":["Sprites/dice/xucxac/Thuong_6",3,1],"522":["tx1/lb_khung_ten",3,1],"523":["Sprites/dice/xucxac/Thuong_31",3,1],"524":["Font/font_time_red-export",2],"525":["Sprites/dice/skeleton5",3,1],"526":["TX/UI/bg",3,1],"527":["TX/tx/bangvinhdanh",3,1],"528":["tx1/lb_icon_rank_3",3,1],"529":["TX/xx1_2",3,1],"530":["TX/tx_1_bridge",3,1],"531":["Sprites/dice/skeleton8",3,1],"532":["TX/tx_bg_chat",3,1],"533":["tx1/21_font_text_lobby/font_text_lobby",3,1],"534":["TX/tx_ico_tai_fx",3,1],"535":["TX/font/119_thantai_roboto_bold_40_2/thantai_roboto_bold_40_2",2],"536":["Sprites/dice/nuttx/xx6_2",3,1],"537":["Sprites/dice/xucxac/Thuong_20",3,1],"538":["Sprites/btn_100",3,1],"539":["TX/UI/tab_duatop_taixiu_on",3,1],"540":["TX/tx/btn_soicau_s",3,1],"541":["Sprites/next_phai",3,1],"542":["Sprites/fixtaixiu/pack-tx",9],"543":["TX/tx_bgresult_xiu",3,1],"544":["TX/UI/btnXingau2Unsellect",3,1],"545":["TX/tx/vong_tien",3,1],"546":["TX/animation/98_TX JP/TX JP",6],"547":["tx1/43_font_money/font_money",2],"548":["Sprites/next_trai",3,1],"549":["Sprites/dice/xucxac/Thuong_21",3,1],"550":["Sprites/jp_small",3,1],"551":["TX/23_font_money_2/font_money_2",2],"552":["TX/tx_bg_qtdb",3,1],"553":["TX/tx/bg_soicau",3,1],"554":["TX/tx_bkg_bet_input_xiu",3,1],"555":["tx1/btn_tab_1",3,1],"556":["TX/UI/board_history",3,1],"557":["TX/tx_btn_soicau",3,1],"558":["tx1/pane",3,1],"559":["TX/tx/chat",3,1],"560":["TX/UI/borderTable",1],"561":["TX/tx/nan",3,1],"562":["Sprites/dice/xucxac/Thuong_40",3,1],"563":["Spine/AnimVongXoay/taixiu",6],"564":["TX/tx/vong_den",3,1],"565":["Sprites/huong_dan_tx",3,1],"566":["Sprites/dice/skeleton9",3,1],"568":["Sprites/dice/nuttx/xx6_1",3,1],"569":["tx1/tx_4",3,1],"570":["tx1/tut_tx",3,1],"571":["Spine/taixiuText/taixiutext",3,1],"572":["TX/bkg-btn_white",3,1],"573":["TX/UI/btnXingau3",3,1],"574":["TX/tx/userTX",3,1],"575":["Sprites/dice/82_xingauA2/xingauA2",3,1],"576":["TX/tx_btn_close",3,1],"577":["Popup/PopupHistory",4],"578":["Sprites/dice/nuttx/xx3_2",3,1],"579":["TX/tx/PlistMNTaiXiu (1)",3,1],"580":["TX/tx_btn_rank",3,1],"581":["TX/tx_bkg_bet_input_tai",3,1],"582":["TX/tx_bg_jackpot",3,1],"583":["TX/UI/Icon_Rank_No2",3,1],"584":["tx1/panel_all",3,1],"585":["TX/UI/hangBoder",3,1],"586":["TX/tx/fan",3,1],"587":["Sprites/dice/xucxac/Thuong_5",3,1],"588":["Sprites/dice/xucxac/Thuong_22",3,1],"589":["Sprites/dice/xucxac/Thuong_14",3,1],"590":["Sprites/dice/nuttx/xx4_3",3,1],"591":["Sprites/dice/nuttx/xx2_1",3,1],"592":["TX/tx/otp",3,1],"593":["TX/UI/Icon_Rank_No3",3,1],"594":["Sprites/dice/nuttx/dice_2",3,1],"595":["tx1/title_thongtin",3,1],"596":["Sprites/dice/xucxac/Thuong_19",3,1],"597":["TX/animation/85_TXspine2/TXspine2",6],"598":["TX/tai_on",3,1],"599":["Sprites/dice/xucxac/Thuong_42",3,1],"600":["Spine/title/title_taixiu/taixiu",6],"601":["TX/UI/Panel_ThongKe_2",3,1],"602":["Sprites/bg",3,1],"603":["TX/xiu_on",3,1],"604":["Sprites/dice/xucxac/Thuong_44",3,1],"605":["Sprites/dice/xucxac/Thuong_37",3,1],"606":["Sprites/dice/skeleton",6],"607":["Sprites/dice/skeleton",3,1],"608":["TX/tx_btn_thongke",3,1],"609":["Sprites/dice/xucxac/Thuong_8",3,1],"610":["TX/tx_ico_user_online",3,1],"611":["TX/tx/sp_xiu",3,1],"612":["Sprites/dice/xucxac/hinhcuoi_vitri",3,1],"613":["Sprites/dice/xucxac/Thuong_28",3,1],"614":["Sprites/dot_white",3,1],"615":["Sprites/dice/xucxac/Thuong_34",3,1],"616":["TX/font/60_Font-export/Font-export",2],"617":["TX/UI/btnXingau1",3,1],"618":["Sprites/dice/xucxac/Thuong_17",3,1],"619":["TX/tx/bg_chat_new",3,1],"620":["TX/UI/tab_duatop_on",3,1],"621":["TX/font/25_fonJackpotIdMember-export/fonJackpotIdMember-export",3,1],"622":["TX/tx/sp_tai",3,1],"623":["Sprites/taixiu_canbang",9],"624":["tx1/btn_check_1_2",3,1],"625":["TX/UI/Icon_Rank_No1",3,1],"626":["tx1/10_font_title/font_title",3,1],"627":["tx1/48_font_chu_vang/font_chu_vang",3,1],"628":["Sprites/data_1",3,1],"629":["TX/tx/txtXiu",3,1],"630":["TX/UI/lineNgang",3,1],"631":["Sprites/dice/xucxac/Thuong_13",3,1],"632":["TX/UI/iconBackTron1",3,1],"633":["tx1/bt_page_prev_2",3,1],"634":["Sprites/dice/skeleton10",3,1],"635":["TX/tx/btn_putmoney2",3,1],"636":["TX/tx/nv)",3,1],"637":["tx1/lb_icon_rank_2",3,1],"638":["Spine/taixiuText/taixiutext.atlas",8],"639":["Sprites/line",3,1],"640":["TX/tx/btn_send_chat",3,1],"641":["Sprites/dice/xucxac/Thuong_7",3,1],"642":["TX/tx/foot",3,1],"643":["TX/UI/tab_duatop_taixiu_off",3,1],"644":["TX/btn_1",3,1],"645":["Sprites/dice/xucxac/Thuong_16",3,1],"646":["tx1/btn_check_1",3,1],"647":["Sprites/85_TXspine2/TXspine2",6],"648":["tx1/btn_3",3,1],"649":["tx1/btn_check_3",3,1],"650":["TX/tx_current_money_xiu",3,1],"651":["Sprites/dice/skeleton7",3,1],"652":["Spine/taixiuText/taixiu",6],"653":["TX/xx4_2",3,1],"654":["Sprites/dice/xucxac/Thuong_25",3,1],"655":["TX/font/25_fonJackpotIdMember-export/fonJackpotIdMember-export",2],"656":["TX/tx/bg_timeTX",3,1],"657":["TX/50_font_money/font_money",3,1],"658":["TX/UI/lineBoder2",3,1],"659":["TX/UI/tableNap",3,1],"660":["tx1/btn_back",3,1],"661":["Sprites/dice/dices-2",9],"662":["tx1/lb_mail_bg",3,1],"663":["Sprites/dice/nuttx/xx1_1",3,1],"664":["tx1/ico_kq_tai",3,1],"665":["TX/tx/bonan",3,1],"666":["Sprites/dice/nuttx/xx5_3",3,1],"667":["tx1/31_font_chu_tim/font_chu_tim",1],"668":["TX/UI/lineBoder3",3,1],"669":["Sprites/data_2",3,1],"670":["Sprites/dice/xucxac/Thuong_39",3,1],"671":["TX/tx_3_bridge",3,1],"672":["tx1/4_font_chu_do/font_chu_do",3,1],"673":["TX/tx/bat_nan3",3,1],"674":["TX/font/113_MyriadB_Gold-export/MyriadB_Gold-export",2],"675":["TX/32_font_chu_vang/font_chu_vang",3,1],"676":["TX/tx_text_game",3,1],"677":["Sprites/fixtaixiu/ani-win/fx",3,1],"678":["Sprites/huong_dan_tx_en",3,1],"679":["Sprites/dice/xucxac/Thuong_43",3,1],"680":["Sprites/82_xingauA2/xingauA2",3,1],"681":["Sprites/fixtaixiu/ani-win/fx",6],"682":["TX/animation/98_TX JP/TX JP",3,1],"683":["TX/font/101_MyriadSemiB_YWY-export/MyriadSemiB_YWY-export",3,1],"684":["tx1/lb_popup_title_bg_1",3,1],"685":["TX/font/65_SFUEurostileDemiStroke/SFUEurostileDemiStroke",3,1],"686":["tx1/btn_2",3,1],"687":["tx1/5_font_chu_vang/font_chu_vang",3,1],"688":["Font/font_time_gold-export",3,1],"689":["Spine/title/taixiu",3,1],"690":["Sprites/dice/xucxac/Thuong_9",3,1],"691":["TX/tx_bg_lightqt",3,1],"692":["Sprites/dice/xucxac/Thuong_33",3,1],"693":["TX/tx/btn_closegame_s",3,1],"694":["Sprites/dice/xucxac/Thuong_4",3,1],"695":["Sprites/dice/xucxac/Thuong_41",3,1],"696":["TX/tx_4_bridge",3,1],"697":["TX/UI/icoNext",3,1],"698":["Sprites/dice/nuttx/dice_6",3,1],"699":["Spine/jackpot/Group 3173",3,1],"700":["TX/24_font_count_down/font_count_down",3,1],"701":["TX/tx/txchon",3,1],"702":["TX/font/128_timecuoc/fontnumber-export",3,1],"703":["Sprites/bgsc",3,1],"704":["tx1/48_font_chu_vang/font_chu_vang",2],"705":["Sprites/vongxoay",3,1],"706":["tx1/tx_table_bg",3,1],"707":["TX/tx/gif",3,1],"708":["Sprites/bgz",3,1],"709":["Sprites/dice/nuttx/xx3_1",3,1],"710":["Sprites/bgs",3,1],"711":["Sprites/dice/xucxac/Thuong_1",3,1],"712":["TX/UI/lineLSP",3,1],"713":["TX/tx/lsgd",3,1],"714":["TX/UI/Panel_ThongKe",3,1],"715":["Sprites/dice/xucxac/Thuong_38",3,1],"716":["Sprites/dice/xucxac/Thuong_3",3,1],"717":["Sprites/btn_50m",3,1],"718":["tx1/btn_check_2",3,1],"719":["TX/UI/lineNgang2",3,1],"720":["TX/tx_den",3,1],"721":["TX/UI/btnTrang",3,1],"722":["Sprites/dice/nuttx/dice_4",3,1],"723":["TX/50_font_money/font_money",2],"724":["tx1/ct_btn_play",3,1],"725":["TX/66_thantai_text_game/thantai_text_game",2],"726":["TX/tx_win_money_bg",3,1],"727":["tx1/tx_2",3,1],"728":["TX/tx_input_money_xiu",3,1],"729":["Popup/PopupDetailHistory",4],"730":["TX/ico_kq_xiu",3,1],"731":["TX/btn_2",3,1],"732":["Sprites/dice/nuttx/xx1_3",3,1],"733":["TX/font/101_MyriadSemiB_YWY-export/MyriadSemiB_YWY-export",2],"734":["TX/font/60_Font-export/Font-export",1],"735":["Sprites/dice/nuttx/xx2_2",3,1],"736":["TX/ig_bg_thong_bao",3,1],"737":["TX/tx_doc",3,1],"738":["TX/tx_btn_support",3,1],"739":["tx1/43_font_money/font_money",3,1],"740":["TX/UI/icon_reward_duatop_0",3,1],"741":["TX/46_haitac_font_money/haitac_font_money",2],"742":["TX/24_font_count_down/font_count_down",2],"743":["TX/f",3,1],"744":["TX/icon_thongbao",3,1],"745":["Sprites/dice/nuttx/dice_1",3,1],"746":["Spine/title/title_taixiu/taixiu",3,1]},"types":["cc.TTFFont","cc.Texture2D","cc.BitmapFont","cc.SpriteFrame","cc.Prefab","cc.AudioClip","sp.SkeletonData","cc.Asset","cc.TextAsset","cc.SpriteAtlas","cc.AnimationClip"],"uuids":["00hDNOD7dOPLSRPNdYAJsg","00tqClhrBNNp6WZfXw6jzb","007uOXI4REJbSdR1wP22FN","01FdMBJNpM+ZZ316pvDAC9","01YdQeZPpOya6GQ3EeH1SO","016cb1AUtPvbl0t2au6WJA","02ClcMU6NF3p+NZGtu+3ek","02oSc8ixRGxabwgrMhzQ2I","03OoeONDVBhKcU79Um1w8H","032ZGVS1xM6qInQ41mSRV2","047lWjgAJMd4+YtndlNKvh","05AvCg1zRI/am2+kIzxvHy","05KqEqGgdOZ65Gox5dBg8b","05K7KHCVpIgaVqv98WLJqB","05Q1TUTGlAK65bv2anPeh6","05YSfsaGNH9rl1KEHdKSpg","05q7F03rVGB4swipD9f+6B","07NRdgI3lKia9j5gL+aUXY","0a8MVop8FKhb+kKidgAYv+","0blvMQfk9KF4wZbgArnUr7","0dBqJksv1GjYyFfPSyHdNY","0dCN6iCORCaKd0DynLCYHX","0eZUyyAG9FuYbIa7DeP12I","0e8cmNct1CxY7JUWZciPbn","0fhjCAUzFNXb2R2anqfA0i","0f2JtP1DhFc6GDPFfgdZqZ","10RCCUrxRL9Kzhx1fbzPdw","10eGYdXelGw6RIdj+JMj90","10hDB1rzxKT4fvTeTf44ns","124PATg3hGCo3m3BChkRab","15iPKsFN5KFLk1ryCZ3JxQ","15vnArhMBF4JgGvBCj4tva","150wpP9y5JO4gNCKBbot+h","16ziTW4XpP/pQ5cN1f1RPk","166gSP6KdHpaPey76dAY7G","19GU6oTPJHYZpgyefH+/4b","1aCPJFrRhPBbelQXSyas71","1aoGuJhshADpuQP8icRBrW","1ax8lJWutKMILQAPI+scBj","1ben4emyZBXKUFAP1BDewO","1cLSkdyxJBLbySE891ghaf","1crR947qNPga5hybPRy7Iw","1c+ZmWHAxLbqSC6zVZ/WWw","1dWBlRnWZCC6CezNFe5S5a","1dWj46/ZdGSpTdQx58ZxyC","1dY9xM8+hJ/YKs5iBZY19i","1d7SsnRc5JBqiigzuY+BXS","1eE5BJRPpPrrviCUtAJ0eZ","1eS7qUUwhBD4EzJRPMctL5","1eV/3BShVCO5aqDciF2I46","1fBWZyWTVIbKCi/dlWuMxn","1fWv+rE4dJnb/b6UJZ+okx","20Vve2Sp1PcoJFH2fAlsLx","200+PZSCVG65qskjb+NjBr","21oHWZaR9MTYSWt6aES/qC","22zQsHr/ZNZpWmL1URxiQ/","226yswcklFm6u2vwdLeDTK","23zLCtM7hGRoYihg0hynC8","2349GsT6xP17yEpZFxCOQZ","24trXV2FVKsKaK3ZVx3f3c","240HZS6ZBHwLwnFbQ3ygUv","25s8JMpItAtp+FZ7b+8qpr","26ZZNNhyxLO6AGnBvGAHga","2751lfIHpJdLqTBApC9sFh","2817fa1kRKNbHlujKyadHj","291x2dxX5JwreuBhf146/e","296Fcths9KcLjeAU21XUDm","2aHA12kj9AtKfKZEPplkFb","2bCWd3gZhJsrZeoykAyMVW","2cqG7BjJdKQ4ufQOTGCxS8","2c9D5t9ERA26ru2/eNi4u9","2ebZ5GvmlFjbPBxtCurdD8","2e9u+Bcu9DhIBIgaRqQmJL","30qV9Unu5CFJ0TNZrIIC37","31QQtBv9hI+4KjmASshcfm","32Pp/wt+BKoaWHhlrHj8Hs","32k/vNNoZLeKVgON84D3wE","322QuTQMpH/7OvouVSkaTz","33VbZy5hhOR7Ko838UN6X5","33fR2q6NdCwJyAGc+iOKpN","34R0ICk11JDqIgHKszUtVS","36GCDikQ9JWqEpNS6j7vI2","36GF6tl3tAUJDjNaiLNbgv","36Ys0cDOVNrqJ/S3okcbYk","37FCJwqzdPk5cJu+jYGYYn","39LxiwQh5L3IwGTi/istki","39wmVFI5hJKpKkWZGIQErB","3aBMVewS9L5pNSFtht0Grt","3aPYWfajhAb72SAn06bR71","3a2xVEqiNO0JCSRN+NUgCr","3a8FIXlgZCYJxUud+kDOCa","3d98uqdx9Gern3GH/XN8H3","3ehxDmkAZAdrFykOHO5VsN","3e7oiRS11Dz6u+KpMFZQCI","3f1Bhtta9LMK9G1E5bH4jy","40vPuIbaFBp67XWh21/lBX","40zL9/hhlE9IcinznxUPsP","401JJg36NCHoTg2WH0EbuS","42Sm/jJlVLq5Ztr8emZRSW","42rUJlHcBJ56XHfy01U5qs","43TXoscRhOEIEqUDIYCL21","43q+tQMelAaYv1IFt0fTOF","430fkg901ECLpw1CTqMNSk","4365F5b+JAOpNJJvDkqru8","453yysxfBHs7Km67NbJOv8","47kV6UdZhOAoOx6O/8g1Ku","49/+sBc8VH8I1FieTOvDky","4bScdX+nRPOJh9OjZr+VZT","4b1NObSbdNpaBSZu5dqMAr","4eLbiVqZ9C8ISbUXgSHM6i","4fo+cigztLi5uoaByZUodw","52AC6NSkxLjL11OCWDaDzM","52ruPlOU1OF4bbZZVXSKUd","56DCgHjnVCKKS7CjCvCMRF","57oh7NEH9CXJqENJ/blrxy","58h7jWuttAa49Oedrn7a8a","580zac40tDo5uB247NswFt","59j3jfNg5F3JxDSF9H3PCD","59wteVhltMAo8ycxV3IerP","590+lxDBBAwZI1Le8O0t7n","5bBHkeNBtBEbW+svISeOZp","5buY9oZ8dPmJcVDmeL08ic","5cGesjTLFL77nVa5c6RtJo","5cwdXT1ZtHcL3tfGnfr6ix","5dOB+b5KVEz495hJ3FEqwu","5dSm4ywetFIJcMP7ce2UQP","5eZLIPHapJua5i8Gl3fnM9","5ezFj0q4hLP6ceX6W4F+EE","5fFbebyhNDeYGeA0RHOPst","5fnGv4A41OpboyYWY5LHub","60OmsZDyZLaaDKKs5ZGrSH","60VoiLLNlGl7tdpdkwhA+9","62H2gUQotDMrReT0wxtPF2","62TF6c7v1FXI908IQSCLyr","62ZPVQl9tJgqfDHxlu1CE5","63HUyK7WlEipkXoCQYdBWk","64kBAOv69CaITIOw4A7zp1","65D+Plvz5AGpDT/sjQ4XjU","65cyrCV0RDMayZ/cp3BUQ7","65oVQzS55JkqbM74cYB5mc","66jri3GZJNyYxAliXygt3z","69xvseLM5FAp1PwdwSecfV","698t0i/l9FC4FvdK5Uzs/w","699zgG4UxLGKOQ7Gc6lBO7","6alEcqgaVFQoXG0p2smUU5","6bUlXKwVlBU5t56CctYTwP","6chV2eMXdGULCPgFgXBl8Z","6cvUR7zIVJPLISS8XfJPqf","6c0w5HPlJJeqD8+2pyP1lF","6d2x5JENhJJLGQlocK6mJ6","6eDpL/YSdKWrA2Sm1NfWPH","6fH39T6blDYr/71trOZLDU","6fr0ubO5dBgrNmxZezuiwp","70rmY9wI9BGKEo1lpo0rhU","71TPE5Wr5OCK4cxeKyaL6f","71fcOnHSNFj5OPbK8DfMnZ","721sQ4p1pBDZhpHRSW3WyO","73/hFIppBCnLwNB6f9lBf6","74FQa36hFI0bV0rMTKACbE","74oMOMtVJM3qWH32NQMTCI","75PfBapvhJ97TjdVlZwenb","78PiDY7MpCGotHqE89JeGp","78UYbzl3lHjruQH09GTB+4","7b8frEMX1FUrHGDrkpfZKJ","7cMTEP5V9FAJXWI6n9Cmrv","7ceqlzkjhIS6tLJuj66deI","7cfE2tBKhH75gox7NJyOT0","7c1x4pL15BqZzU13q3ahLx","7dkYg4KQFPt7pdhlvg5acw","7drszuxZBMK5XDGwqTWrtH","7dvD7IoP1Kq6eFvI5/K2Nw","7eaFOmdLBJoZKypewKRT1E","7enXK8mSZDQY6n90/UPYxH","7fCmpSCZpP+Z4QJSWn9XEy","7fHx0oitlH2o8/VWS4rOe9","7fONY7ekVAOoNIyt66aByn","7f4nlUEXJDyoKOl54SBDg9","80F6cnnh5Ms60E7KvAvyvL","809CyTJBtJ0YJYxCkTGmvN","81hw9uqBBO94a5LJxhTO6q","81ycMLs/ZKA7bohvUQ+pEr","82BVcoygZIBInKzFsuLfIS","82Cgb68t9F7ZUC7h5A8Nsp","82FuZdNdtCnoSoRnzF1yHm","82ivvnGapLD73KYxz6PSuh","83FwWvjsNEErPKUv8NLbWt","83ataJj+9CkZdvs/pi6r6e","84JFs3bupGHbteLkv+IjwG","84xT/n+HFDBrdYuBUmrg0m","85Av9tts1KzYn+wFZIFAhz","88gUHEE31PpZ1r/etaPAch","88u2Btzr9F44onL5xF6Py6","88yfPOKFxPZb6zjbpsnyke","89O6xKlSVHQJqz3TFjGfBj","896ffCEjNP7YYxhYBJT59E","8aH0CHsxlF+IElupKJV7WM","8aKZF9n7pHk7D6nc05wbvC","8a3WftZhJLYbPvXRh5C3vV","8cRr1d3ihADbtIO0CAM4dl","8ezyXYBT5Kc7N/gBJcf0IL","8f6kIHkB9FLrfcQf+hEA/G","90Cr+F59dKHrw2vyl5UnnJ","90KMUW7sNFyZRJmiJlWNCO","90MjkBRItD3ocG8VQMG8yb","90jKwgumxAdZWgT2wKAIRE","90sE386MdJtZ7IHlFUD5yr","91XSAyzmRKYoY//RP9Yy1e","912dAiyOFBs7UgZkrxiZvs","92PEN4H21LqrElRsmUE3Qo","92Q/gcq3xBK5h00yGGSXHb","94Ly7RCMNOgbNnVQygcL80","94dqbrFgZGGq9NFh6+ebJB","94hsI1kdxM0bN7bljiexyH","94/J5d34RNc4bMolKAtDJ7","96urnpAsFIxq+zP4MjWHEL","97Lc7pNNFKFauK/WLwBPnw","97rHtye9FOi4nZrayFT8+j","971kW4HZ9PK7CUjx0uGs4c","98IpHfqd5ORIPkpGSuawP0","98R5E/4KdEu7I0BmCn8IiE","98S7hqjUBMlqfa6F4VUckr","98devNf9NJr4s6dMilV++T","98us0JIetHSpYh1XqsueCr","99DIkzsMpCdbelwTvujCTJ","99n9m7gIpA9JKdNz9Vkl97","9b8qoSdn9Jm49PYWvePH23","9diRkw1hJGebbGfK5yjiFR","9fQurZCtxBpL5PIlGkGWYk","a0T5VlvLdJX4obQ7EBqo+v","a0eWV6eGNA/Inj6E+NgnS4","a0g1sOljxHoqO4++c3mWkR","a00C1JFtlKyatXnCqTiLvL","a2uUCgGxRPGKwhZAOI4qIn","a20musyutJ8p3jR3gkwUpY","a3ORqzD/ZHvrhhrFFDD8ya","a32DVUqNVJ+6B8ADlr1m9S","a4ls3/9vlDsZk9KpkxcUwy","a43l0COEVFi6CtpMhvRZOW","a5pk+VqVxKfKAM7rwOjMKS","a7CJJ3mzBKdbOW2TVs1R7g","a7UtHS6j5OO5rbQTe8N1VX","a7alpbKiZMTrT5iiO0thbF","a79+F5MsdM1I6sHh9/mieB","a8umIEsD5MdqoA0S9hZmSf","a9A66oJYJCpKZNJUkZCrmP","a9C5HfxZJKAa584EXnIADH","abZNq8wfFB7524FIHy//jm","acVaS7E3dJDbL8si+wVke+","ad3ckPsZJOE6vwaQ+rkLU4","afDT7fPLBJWqZplKHeK8N1","b0UzcEcZxNjZUE+JH2SlwY","b0tojTJrtOYYqZoU4ZMKE6","b1LKq4U3dF7rKhNSbssmmA","b1XOB9jGhB7ok+2vsijsQS","b1X+dQgn1MKo5D9zTcDyz/","b2dTBkWb9PPIY6H/jHyg6B","b2oHhF5U1IArPdURr/PQVb","b3tl/0F8tJOo2WK4AVxT9N","b41dlJBxFEeZ61xX2qTSvp","b6PunMka9Bs6JWR+0lxVIe","b7iWmpvIxPfIRGMP0+bfd9","b8R4Ml5wNA2pIvU+VPuYKO","b8XQgqPQNFS44oguzMHDeV","b8jglxBOtOI5WaZL74+Myy","b880AHCGlKw75xSHw+U+V0","b9GrIOTe5EJJ++JbzZoP3K","b9LY+IXTpKM6xg+wvz21TT","b9Yto0/uJOc6Krh192UOzk","bbGdwyZyRLyJF3vige9x9v","bbJPOYu9FHsJTEt0d0gevn","bbXDDx68NEwr19LcdHpMDj","bb+r2+GFpPxahwQi5soEXu","beHzDbnklGLLY9GqTEuTxY","bfXDIFLJ9Fp7aLHOIPhJa2","c1bXRcmYFLV78OYF8jkUcW","c1jd5gFEVNdIdv9ldP3aI1","c13buGzstLPZE2uryJwmFl","c18slXF7pB1oZLPtfQ4/mA","c3Gns98vJI7YDnrP2zPhST","c6/StxgshDHbZzhSQseSNJ","c8ZanVrPxAE6rmg/Gp6+cN","c87vX5l9hO9LHaFzeX+0j1","c98TH2d4ZOKZ742dznK2h3","caUbGvsPxO6o5OIQF61gok","ccQ60DmVxHN4W/o0rVNB9N","ccwK9wm9JMLrDpGgZ70Jx0","cc52ZctNVP3oULCokmExTc","cc7KRDlqVOM7KODzr0pywH","cdUjkOGv5FYZRhFY9+9rQH","cfQV/uQ4tO2KxlxUpmR10W","d2uo5HOdhNHarj+zUHeNyv","d5MsRe+bdB3JYBqeHqi4nt","d5dD732WJE7JPSGTThpQaP","d6/vx/zs5BW5IHmTLt40Zx","d7CakANFBO35+B8FAMWSru","d7MNM+g2dLd7S/gy41pdgz","d8zzOub2RNp6/fG9SdrM+t","d9h0MBn3JB1L7+7e8L58v/","d9jXxcmEBCaJCwK0BgAQIw","dbRkqWkstOVp1CbkCNUnnd","dcf1ggrwpG0rU7Z/8naxcJ","dc8G0MfUFO3o9L/n/0bcfP","ddBi3l5fBBXZtZqw7mEXe2","dd7S7J2C9F6L0GzRSV6Vpv","deV+wQJQ1JZKBlxZaAwwzB","de4ttMxLRLZ4YscS7xuRLm","e0kcBvOl9GvaScAxEv2XaS","e1lvhp9NNHS4reBrZ/+KQS","e2Saa/lgtEsZzecno9LdMK","e2jrI6wh9MBoENIuKOzPx6","e2zofaTuVCkrWUjgquRlvg","e2+PQJcN5LR62AKWhZkLcB","e3dDClOaVAJ51db9AOx24y","e3gzYy57xIcIdk+Nqm7WHA","e4hDlrwSFMG6ypoSZf8z7j","e6x1GBX9RDOo90yta1EsNT","e7I+4/n2hLdotCqMTsDXyx","e9k6f3lJdE/J9YQgR6QpPi","e9/+SpZK9P1qwObg3OWHkg","eao2XPFRlF9JJPukzVNMd8","ebLBa0yxJAdK1njicSp8OT","ebM6zwEuJBxoIV5wDg9wj0","ebwetQM3dOcqej8Ird7iKx","ecLDpSSqZBwqCjqoia4laS","ecNWM/361GWLztlc5CfejL","ecURZWFepE67KzR55P4xjW","edLr4qTWZD/oYukr60NJUl","ee5JvjpYhJj4DYO2iYG99l","efJwO3uchPVKnE7I2EtIod","efUXpFaTpE1Jq/MslaDbbZ","efw1UUMOtOu7gMRfY1FyoE","f0l79Rup9PZ4TODXApQ/g8","f1mA7zZGNFUqh5fJJHW9U4","f2BGcAfnBLUIJRqSTbLLY9","f2JUW9VSZLB7nh2WyscI9z","f3MwMRgRFCFLn+pDRYcrMJ","f4evhznDBFj4Gqh+pm4r3K","f4f8ahCJtB/J+dhmJtR1so","f4mJ3VfNNN7IEC8AzAaEzV","f50vms7OxOQa7kwwN4KQWf","f7xthm1O1Jzr9cL8Fq31Tl","fciEK5YQJNGa7o5ODWFzq1","fdP/jBMhJAVokMjB+CdtYM","fdkgmBrvpETb+GAzzU6aLa","feQ+oeZMtCybVpAFCoSY9g","feiQGmlnlOSZ9CmHH3HoZG","ffSxqptONK67PUGdklDLvM","ffS/CCyL5AgouS/FLgf7Qo","00QsuDCPdH8J285UZYRtKj","00V7QRvsJMOpUmkuHw/Wck","00/X+zuDdCo7K3NnrYxsDh","02XtK0it1MY5s3LvCMdd8B","02abj+UgNLH6ZAWioxNjU1","03TfW0oRJLd5KhYK/hbEA5","033rS+5mhBc4V6dnfpTKWQ","06FrixNp1Fc6KGN26ijHsX","07RMpWlZBKXYUNm2fKsM7z","07lbNRDwFBeav151fHyLxQ","08SXZ1sahGcbks6xf1vZdB","08uP436CtNEo0YMQD49/9s","083I7LGMtPCL9QaarHZ8Zr","086ZDt8plEaIQ/V49eY5rp","09jHRsjv5DDJJrc/QMKsj8","0aSNES1fdEoZ49aJXvi9JE","0a99aJc2lA16xdJIVA+4DJ","0bdso2EcdLHITQLsT0W9vC","0b3QmD5EpFUYuqvdbhmUq5","0b+GRdVyBAC5r2zC9MzU2Y","0cAR/hj+5GgL3tfHQl2ZY7","0dfu2ujf5E8otfFtlFUE5C","0eGgGKJkBLc4bunNYt1GXz","0fInz96rdFR4KBku6m0AQx","10kfsfyeNFGI5C/ucuwyvG","113Mdr0w9DM6BJRcteDwaX","114VPjkhxPGY0gSzQkKJIx","1196FGZzdHGJDQvaObfHLw","13LoJBWMxMp5Dd375kpClu","13jo0KXPdPfokkbjwnrMxA","134zaAYYBOrJ0QFhBRl/81","14HkypE2lNub9ujsHwClUw","14UaqifypFBadZHiDemHKc","16Uiw9y8ZGabdpdrdomGkK","16zHS9nnNDS4z63glQf0qx","17OeWr3ZxJoK6dno/7XRTz","17ae5A/xNIrbCoqaEZ/CqT","18sdm95M1Dq5Udf5/KDVc0","185wst6cVCIYILOtsNXXru","1bFE18nYxJo6omNWLSsyMR","1cEkcwC+JKkIAXy//ZLqbN","1dVCkTs3BP5LfO3CEtBy6f","1daM2xir9D+7EtYXAWTnXs","1ehFlNX/NCFLzkjEkvTdu8","1fA7524UlA2p9+6VS0KUOF","1fNbHOVkhPFYr+QP2klkVn","1fSyF2+QlKV7q8ZNU1rGfY","20uc6gHVxDqZk0hfgofukR","21EDHWnjVDO4wkWE9coBZH","21GY+TT3NKdadhuO183UJE","21Rc5Y8fJAObdprjE1ZJ3M","23E2xjo6pEIJgkvuDrasBs","23nEclvGFCvI2y8BZyYYE6","24IZMKRT9DmZRznqPZqKNE","24R3/ssphIabnIvEVUlBrv","25vj9LaLVA+5qyus3cl8Mm","26UMVJ7ItHIJ6Mdh6/SHxu","28AnDPbQtPurF/xe5HR53z","28EZbJzn1Jg7DjhS+5MVvG","28fm0T5NpP1oXE35CQ2DiK","28ud6m2bVAzbpSKzijBLsY","28y+q50o1Ci6RtaBfS9Psx","2aJBeqGt1MjICbuBTwneKF","2bnNgUwfZCZ4pz9s6oOJYx","2bnb66golLfrg7P1/Oq3nA","2cFTpQ3WNILIuRbqmxY+Sp","2dvMj8v8NL+pEGloIGXCmE","2dyOB12QZAErxhXf5LUBfF","2d2TjQzZ9AYZYT3YdTjw6S","2es/9jaqBNhaViMQXo/STx","2eweembQdBGYx/DEMfGHVZ","2eyZo3en1J3LYTCrbxY1hM","2e3SP4/yxMKal6uT/4nBqS","32sd7EWglAaruDhSnOKfhp","337+eJ7zNNcov6uZm8xc5K","34NJrbDmREPJf4vDXSSsyO","34XAA1BLVLr6QX3WD/IExW","35wH4s+c1MkpofHMsqyuLT","37sNCeJF1GpLIeGzyEp590","37yWjacadL8aAD6cvhGClH","38wFD/uAdK1Zrp4itGRki6","3avjM9aXZK3a17k9Ew3Jas","3bEYjrXZtLgb5m4Vjcy8t4","3bkMzL7wZKbL1iyB7jIh8K","3cctn5SVlF5Lfbvo0S94RQ","3dTCErKspD25nSotTfz8by","3eE2lab5dA5ZIHSle15JyQ","3eyOcmmrVJd7tQn4IqPuH+","3e1k6SOINMR73yt97fVu+T","3fo0IZTvtGfK+ANtet6z69","40ZPzAlkRDoYBwIQ8zZVxi","41Aw1Z9aVJJK1FydFsTcYN","41bJlr0FdFYrT2wuL9gOmH","41e1oW2t1BEpufb9l427QR","42Dc//kdNHapOTOPdgMIKK","43RLktYHdGzYLRu9XURtih","44G5L+7StPrIz9BNVVbklT","44jY4DXLZA86WzDcyfzjpf","44nXX0vCRL/YcISQ67Q4eC","456ImKs0lAUqzhfPzULGsM","46TpYunVFIdZzp1tgBcwSX","460MuPvztODLMqKh2FuAKo","47X6p5EiNEfIoTVt7If9yn","48U7hlSU5FxrDYBaOGsvUb","486Ab5qAxCn43ucY2VRIl5","49ELje2U9ONI04tK1wmRMg","49h9fY0+BI/IVrLo9vEqR/","498KfFlMRBmqjvGAVnq3M5","4aRw8nAtBEm5RK942ilECt","4b8KY/cLBBSbo4TH0UjO76","4cInHSfkNDcKPch0UWumz0","4ck4akNchLGZcWc0Jwxm2z","4c2oMG1dlI6ocM9Uyj9W7Q","4dof05ZRZD751vrFoxDTXQ","4eGm1hQP9NZqgi/R1Z+bUj","4eZuaKNdVCyZLQWsPYpjJi","4e3wH+CepJkJPxxydOb3m9","4e580PlC5NGa8nvtG5/XlQ","4fIBCC86xBXq89Bs5xp/0n","4fIrwA+xVPgIjAKfM9jEUQ","4fNvf2xPlFEYOpv1D1X3Jw","4fUBMUYYlG67mRox3VZH6m","50AjqcFFhNOpPHfB9oNtMm","519qjQXBlKWZqomiy4IRJM","52GGgddV1OOKb2fymxlQUb","52QY1oi1tPgJK//AXFNQId","56WqPjMKZDvqb5J8osi4Ed","57NJfvkyxNNYrpEnTCdDr+","58XoT9vcVI/J6Nl3QmSAb3","58fBDuTItIhI32PNp9YoYC","59Br6mHExAb56qIUbRZtTh","59RMEPWXxDO6briQA00y7y","59ndvrjlRCNajJeouqcIP+","597vTcIN1Jo5RqeWS477It","5aT/Eh4r5GbKfY/1eiWd3T","5azB5mVylB7blrTwS9WUz6","5bR77osChAuLoICMn4eIbv","5cKahD9uVG9YwulCwCsgkW","5ccmeQRPBJdrpoN1TSatWj","5c0ZslWtZFIpmvDkJmFyst","5dKaGm275O6bpT3ehxLE/S","5d7CI9GlxGt6PUcO09O7FD","5eGu0aMhNI0o4knWzhtkz7","5ecUWamY9FC6HFXaCMvTti","5elp288XJHarAq4Lt9nWTa","5e02Dc095CrZ1vHkdrDePJ","5e7UqMWEFBaovOqJCK+OB6","5f+NxrTGNHArmmQzZRafp4","60UnMrwvxBWL7xpuHrj9bS","62jZjOVDhIrIHKV3/BDtct","625RIB3oVPiJXoaA4VXYcK","62/4SVSIVILowuZ7YOuCgZ","63kESczV1CIJsNq1xjZoBm","634REtQuxPkot4ymdXv7eg","64Cpjpz8ZNw6To3ybolwXO","64iwWmd1xD7p+LKV0ByIYi","64n43nHLBLb6RSE4s0F+DW","649RNc6hxA2qwLrQxnmAPF","659DGWQORDrZQY5/4C0DT4","65/MGeYsxK25My3DvCfMEg","66uWgFOvpFl6CPASu6xa6a","66xLY2REZLnZe4KlO6OZT3","67CRZQyOJF56ergDUTgQ6j","69bO7U31BJqZ2+TOTo6Gxr","6aXiYiebZBG6z24PV0PtW6","6bSOkpq/ZJYY/D6UtMJFnd","6bV5N97Y9PTaLfw0PK7aUl","6bjc7mO89BR42dAwB4Z81u","6dPFaY519DC7vxm5rnbW1T","6dkJhjI1pLDYj1tmTRKtYI","6eRMWcEeVJIoLieegittYo","6e4kZ/NMNFCKVfgv8xWZFv","6fWu92o/ZDk4xuY7niE4XS","6fyUaXDSNL6b1l4AGY9JkN","70YH7kiPdIeL1NA0+dqxod","70YJafqJpMg79XKLwthtNH","70b/cUNjdPTY0SM36U699y","70qgxGiPlIa5I05cW/+tW/","71xrs/z6lFto2XT1h8DCiE","71ySBhFPtPiZlGtW+3tmqp","732iDXIJ9AT4MZ/vLWxrjS","74BwQ06RZFyJ+LjLgMb+Tc","74JtkxyJNP87CnacE1LGpF","74KjrfTAZPqaqNWHpqDo6A","74NEszG+xKFJ7J19nhITEw","74cr+UjlJN9LcUWD7SA9vT","74eSDKvsVKR5DQYtyftfPe","74p0tsI4NG+7l+L8/yClQb","74sup71DVBr6oLj9V+2Elz","741953FXRPbKtPyJSVNUSl","75nIirBPtIcY7JLTvAclse","76BKjwnpBFh7D+kXqZypBD","76abDbdSlDSoi2Zy6RTnF8","768nBCuulBDIgveueBKGH4","78i7lgl1dLbJFBidH66Iqx","7ad3yK9yRKcayWa6ng0qqd","7ayk/p4MpM0I/wNGHwAG17","7bEsrG4wBAoJxMauqy0UHh","7dgkb8Gc1JnaZhFfi3HQmq","7eqv0C3RBLdb95/sz7y8Jz","7fjYq0rT9Ok7RyxDdawOcQ","7f2MVPaYpGyrbqJsV2FD16","7f2nbyjdJOUJtPYg6SVGHh","80lPdekDhBDZKEM4xGc6l9","80xn2oL8BD+LyKwy/cbYlU","804HMcEyxDAI/q4DPz+W35","82w/N5BP5HDpgjiaV+mWlU","84AXX0r8RKmYGvrWvbmI76","84EBzHqRdEUIxCI83X132b","84F7ErHm9Ei4vNOsH2g6UK","85K1fmWvtNfKV3faru1+qC","85wzhCHqlLb7F1TXOwqoML","86Ft5R9TNN4rqoLaxCVP7Z","86QHrMiZxNYroTVKy+zj9d","86SwMG9OlGSaaCraXWMmom","863Bqff3NBH49vU8qmTl6L","87qX/KnWNCHqsHBWIjGmfh","872JLJW3xOgqyDLfToDb2T","88rViIxU9JoIi9S32b/6Kd","88ukuVlqNA+5hStPoqCif0","88396bAe1NfpWw/FLsYYF+","89URE54yVCb6PHy7PVsnnW","89x+34CkpC9KN9OsZE+vC0","8a9bZmk9RGxLKZre7YTlG/","8bAhY2hzRKHrvdJdbNA1Y3","8bHbgvFd1Lo441yIywRPyV","8cFMvQMxdHq5E276DUCPx3","8cHRV5suRD7J46/7munVco","8cegrFWBJH55LvWGFvI/Ik","8dGLlz0yxFpJVz7Rvb+Rf7","8dJoihrAhOEKPHmwNuLATy","8drB7vbaJDXKW5oVYIrr18","8eGI6LLz1CdogQEw1etUdV","8eW5ga3DhKArs7TsdCqj2p","8egWTnrcBFoZ4K9HU1M6Q0","90cInoFCFLv6vF2lkhvC8z","908ItJc/5Ka7hQat+bnDm1","91QID7+/hKxLBXNt06HxPa","91SKOr6vVPT6iDBVVn1p8s","91+EQOO1NJjKdVNU3Dq2VE","92I7lr9gZFaIoO0l2Oh1oN","92xPER1KNCmrTDFEWd7595","93dTA1YqJOr71c8peQ6ZDa","94R4oxYhpLT6lzYTE4R+Y4","96nmLIfM1KhqmX2Z7P55ZD","97qtiACcxD7ppEv0L+0Xvj","98lEOE65ZHnIbrxh0TpdF7","9ayaNEZUFFs7CXsk2/RwBF","9bRQzD6t1GjLuK812H8Qj5","9bUzphyZhEDZl+P58MxXjC","9bdh95/ZNP3oVSrQAWwZ8D","9dHGb5pXlOx6uxVwV+8alu","9dhXu8B+tNgbgYvJUTgpYE","9d252ZcT9EMaBTrjuR+W/4","9eItFWvp1NDJygxcUNLM2r","9epqS4yvJP0bcYp0i7GX+Q","9e6y0uIrZLp7Dvsq9whmmw","9fosvik1hOVKWsX5DMGhTZ","a0U6rYCBtLZbyZ9DgkGvOo","a0lDHjaoBP4rqBpzhBlVbX","a1m7J+dctCZbdr2vnSjYTN","a1oQRjERhIuKHy3UtvWuGe","a10NVC+2tPZqdGp3ypzX39","a3d2A/V2NELb/oulsPemKP","a4FP/j0ZpCrrAJSBjmfXGt","a4kHxrYXtNE7SyGTy3rZjY","a40AQas49ILYgopUgANtxs","a5mZ1Y8XJOPYVk/jYB1gRx","a6LLXHMI5Bf7d2xkuCavpE","a6cafzap1PgqaUj66mUWJN","a7TSvulO9D443IsvltcpdB","a8y/MVbHVGspoUmrwQBHdf","a86TU7PthFYrtxezvrizLd","a9+8maREJESpVa7lwMvFAq","aa1KSd5nVKe4G+2d6+mUJX","abQ2VhJbtJkLWmYx7auG8T","ab7IWFZeBNuLZMLNgFRXnP","acTphFco9MZ4acizaYfTxH","adB1Opp0NHAoBoX+XPMg1d","adb6wQRohCYLSbHDk7rI6t","adhK2fsypANb9wS7petv2X","aeJMkBqMJF554fo8E/paVH","aeKR1hnENOibqBD292RJTR","aeKTsO7u9IepWq6ZoiHgNc","afGwk3rO5Cmaf6fs120cXt","b0JbuhcaNKh7oWJriPVFQP","b1GycPCkdPh4bz6sHzM0E2","b10undFeFBvJPU3JrZHO62","b2Qc0zhF9LT7HYW5TgRWlX","b2euE7ch1N/4dQPwqSe3FR","b2nbuKmgZGlLM7vkes8ijo","b2ssxn6lNDa6iU4BaMvNz3","b3VGWHPkpJiKBZ34Vo6jwj","b3xTtr2jJNlYFpHwiGghI+","b4akIEJhxI8rbjghYq4o7W","b4l8VeIkJFqpIaS5uu3Ltv","b5mJ/AGpRFDrD3voVjR/4d","b5odSCvgpLhZ2+lnWyjGmu","b5sAAVniRBRrvUmshNyLAP","b6b9qK76RMAZpEzfcpoNi0","b6mbc8TUJFhb9K3gFDASRo","b7rYiqNCJGBIl9n7Px1/TK","b87RwsUaFLv7IhS0kVQ/0K","b9hycPcMlDBaO4aKEYrJN2","bamc0K7ItIhKWa3wk+qro1","batekzAilA9IGQEKGOdQvS","bbTpDxQB1O/LSH6Yc7DyPB","bbjPKK/blB04R/c5CNpda1","bcHbyyr/VG1oRAFffvTGXq","bcfSF2Dq9LGJrA6B5qPRbD","bctUTLsQ9JcKkKFX/J4VP8","beMobX8hBK9rLQgWhJlvLh","bfAL6rcMVBjJSUKKiG/FmQ","bfunBhm7NNSbvqlJcYMqeZ","bfwRgFtEhJJ6BnVQR2OzYG","c1kvyqqy9NAIUJ/yGdoj0F","c13WelVnRLe63VhH3zqPy8","c13jNWpMBIFqKET03qcCIU","c4D1faAqNHTb8SEXhEaFTz","c5D13TlBdKl7qUSUIK3gbQ","c5SCbquspNAqwIJKznNuUL","c5fhJ5DrdB+IfHfBkSNSUn","c6DviZL8tMkLlU38OGmgu7","c6nBlu0tZJg7+Dr7b3l5Ju","c60J6RIPZD1YjOKlVmDLDZ","c6/RiDd/hLiZhnm/vrEOU7","c7ZQLUx4xJybY+jaWaGav+","c8Iuuf5JJNCrkv1uRIYt8u","c8VIx6hcFB8Z6zynV/nLo2","c8vTpIbhRGVZGLHUUTW8a3","c8//e18YRIZawd+b0KiiAg","c9KzQARepM+7+IIrywHRxQ","c9c2qKA1tLbL625HAaAb27","caLWJEHddD/I6Aul2SuwK6","cac+0GP7ZDVK0m902JvUWa","cbqVHRcLZGxqF3bBhcJoLY","cd9+XR3epF2p4XHRL/YH7V","cfr91t8SNOsrJncliW1UwS","d0A0aRiJBPfbFgakt3gMku","d0TJ4ee0tDuIR2o0XcUykm","d0T7BRnCZPsblSCCDWiuEc","d0eOY1jUhK1on7/liwcjns","d0hK0fKaJMr7HQHxG11q7u","d0jjNnxmRBIbTpHLXpTIj7","d1UwtYVHJISKzQ4AxHEbtc","d19ZodeBdF8ZLbNUL3xuVE","d2TfH5iMpDFJvKtQzDGlgZ","d2UI932OdCA4sHLj2vectF","d2bSe1ycVH1KVSl4XMkXUq","d47YOlilhBDZeHPPirUpXU","d5POPYdjpIhaauOW9gYQJM","d5zTJRfldLJp5DIaaue9ic","d53IAicxVHx4dcw5F9c5TY","d7JgAbqbhFy7v3aBlAaKDx","d7+H1Oks1OwZOvsOo6xq7f","d8NKP4UoNONYaTUdXcVdad","d8m9S/U/FOt6zcGW63p6jv","d85HE0typMKLAT34V51bNu","ddrfJQyZlNsLEWMOtWBtSH","dfC+DGL0NF7IqmuBioG4nz","e0aNpBAnlEcbVTGJEPX5S7","e1Yum801dBkLOZ2F8HmCHo","e2ryRuPw5DnYc6880vTZ1k","e3M+TbEVJKsLGCxAv2xYSR","e35Nf5qr1Ml73dps9Njshw","e5RqSpwsxH5Z+fkcI2/Y56","e6F6Y4bT9IqbzknY5tnW5n","e7DIje8m5DkoLikH0tgduA","e8H1RgF5NKa52hWY31V6A4","e8NGEFcx1DerHqoaxN+XA1","e8pN8Y64hP+YEtIwRX9Qln","e8zExuOH1OK6IQldXBcNIb","e933IWsG1MIJK+nE2tiSuC","e94QyHQtxEP5nWNLqhpEHo","eahvQPeHRAjLlD/0uONVou","ebjHwl2qdDcLVYGEAOFzoU","ecU4HVUCdJP5arZlB5h9pb","ecvr8ska5DsqxqKMohMqdI","edFl1u4pVDJr21I0GfE9T+","ediEzSRttHi6dztF+/ko98","ed2aB8qCJBio/BqQmxOYXA","efmU4VtXFMPpQg0cazzlSv","f0U1BXkrxI6I16UNNUj8qS","f1TL1imy1Jf5VxyOZTVgZ9","f2bbqFjnpOvrAZrfWlEGk4","f2w+dvb/tDpppkoRNDMRRH","f2zd9ILf5EjK/ZVXT2rRTZ","f35vPcqmZNuqT+jpAJwWlu","f3+uh4Qt1Daa+pK03dZEsu","f5yyApxMtGa5YGzTfpkHe7","f68tEZi+dD+4GmI25z24FL","f7tjOTcetOBJ5OMHSZc6JI","f8wV4dHANCI7WAREjM314C","fb6UyRQexM/4A7ETzFUYVr","feES+qvbtNn7AN3NpfcnRM","feX8y9gTxCAoBHzLMuphtv","fefiEgkn9JxrKy9sw4O10P","ffSOHb3SNGGJZ+e0zf7YrS","ffw5hstFBG25ujRzHxybbV","00IUS77X5BV6a0lVZWA71b","00pDzEXR1HVKAaKf+4ldgr","01TowCHAdEeJxmO8yAht0P","02sXdgL8VGnaSUERDyLO/a","05APPY6AJMjpT//WWLVY1/","06PKg/mEdLv6fmnisqqJGl","07/u8iYStCT6Z4s8ehlCwe","09Hw9vHTxFibG3knc4t1n8","0aiu6sketKg5IUCvIOAfd7","0a+ZDW6EhO0I8mG8Ve67iS","10oWhsXx5F9oR0zv6EZB3L","111+ud0YZPX6vVcnBKbqaN","12kCYje4RJULECbn3uMo5a","15Ij7YrXtGAKmpEAeTracU","17Ed0mdb1LtqEluLuZdTG8","17Re6AgZ1Pg5H19l7XGHyd","19HHAXjKxJvaGE53pg9rPV","1bHpl0uwhPVZ+IvddAWwZG","1bZRwQLqFKfJxlZPUf3dbn","1b7I6RFH9GOIMqWqjLv3Gj","1eNxsUtQJDWpJsNtjaI3BS","1e2y/2YEBBq4RiYs5nZLFT","1fjNXxgxdFcK2VoJUhovzJ","20H0E3671HRr+WtZDoBaLr","20iFVP97ROC6qtvzC8vwmU","21ILvHTaVNO6ZF4e2eEW5y","219zznXDZLcLo59Nyz5MYT","23BG3pFoJPb7a5mjUjpaA7","25TFK23URHxZN1sY+npfOd","25qeK523ZHGqUYHIIVvn3d","26CzVFGDhCr6M5fxFYuTWu","26KHABfntCRZ6eAOWv48Tk","287F1ZZ5JKBblhmGUMP/Ke","298GtWkgpOKKxNg8ogfAWl","2crHtAFVNHfby72RJi7skR","2e0xCDyvhGzbxOD1QqamzK","34a7mZlh5GToUkjGjuiO9B","34bMjykyZMqahLt2bYu+51","34p+k1EztPdKM/tblhQ0/I","35X6iCfGlDY6WlO9UzB6h7","35yTCcnGpNe4AvwNC8XcqP","3ah12/kYpDVrPdU1bsdPhi","3a26RSNXhDh4s1RFFSAMRX","3b40fOrwJDlo9s+3ZOLP6y","3cS/TM0I9DbpA7XpQT1gtM","3cv07tUMhL+qNrlJEcJofn","3c8qa/QipKpoZwgOpnq8Su","3dBaZNuthI7KnRIb5K8L27","40Oov1zvZODZ2OkFupuukh","43po4/k11HDLRV1W55ImUc","46YGlbX4BOh5ak+YMLFEaH","47ulPLwh5KhaVDY+4d+PPo","48xQ11AiVNebIviqp/XMub","49KdoKxaRL+7UanYXrqb36","49qyET1r5F67hmPEeEbMnA","4cWzgMlA1N6LVLQKo0te+/","51HK/wN3ZC57YLW1EIL27p","55c60BdfNFT4FN7GxMcVY7","57QvURhFdOlaSQKNffTBpe","57cuzkJEVNe7qBEludMHEy","58SW4WHrxINoBUhad73D+9","58jKkmQFFEpajSFo4BuZR7","58+vtoA2BJd5Llp7MJ58qI","59tiRY1ZpJfqTYubnl26kY","5bXP4mz9lJircXyL3bAYbl","5dNqsEz6ZCE5jXnNOJWWV6","5eLOKAuMtKFY33xqorWJt/","5fbzVT/QhBB6VXqtM3AP0p","6172RDJgRMm7V7QhKM4fIZ","62i23rIw1J1L4Z6zFFWyUo","64NJ+a6QxNA6oQYXqkc4Nl","64TWhTXPRHxq4B8GzeYVfh","64yANT5VlMqbF79FgjRQ+V","66iuZkKs5DLKB64O6nn/Hw","67utOq2z5J6r0wJEPB2eSo","69MKMG5v5ITqCUP8Vmmq1F","6bJcrYjK1PpLktpbAYluzG","6bODRb6hBISZUA4AMLX4vC","72F2MlEotJf78pR7W5lhP2","72htsgnBFAmbTmEoQ0H4En","74wANTNjVIuaJld8SZZyrF","74z5N54O9LgqHz9OXMouTu","76vXTqj9pO3JDLhR5T66/O","77cU1ITWZPTbC0a6cmkeNX","78sMrYRs5NbJcr3vFudpnl","7aH5+FNLFN8oS4FwMGKVOZ","7a/QZLET9IDreTiBfRn2PD","7b8WpeYjdOz5pBi2qin2kN","7b90gWNy5Hl68S7Q84ooHl","7cFD6UrMtNdaUuVlibJEvk","7fJH64gdFDJYrxrD31wlIT","81B3ecRkxDaaL4sE5a+bKY","82vaNT0cpFPbcKLqBXk7pc","83VrXe18tKq60HjX+aSwB5","84UzkywiNE3ptgIMYKobI/","86LV0cDe5BbqxvKscas9ts","86k+llOg5DG6TVoJAHJOBK","867glHdkpCC64rn+PHLZsZ","88sMDIE6JOcZS/46x8p4pb","8a1aoZMqhJ7KjJO7gJu1G/","91JSLF3BBFVK5RGoL7CKuv","92qMfm9/1FoIFV4zX8AbWr","95XAYG9OJF8b64u0q3Nmfa","97CD6738VL0pC2ARwQ1EO6","97FYLHmIhBrIU0L6KJ0mLr","98D6KfN/VOu6bP8qaCclB1","98dG6XVbFIpJE1crS+8bWH","99Qo15xQdI7rUWi8HRAnTC","9dM9NQpj5I3bcDPkTHLM6o","9d3EY9XVdFjqefgpa3p5w/","9fMmP745VDZZYI44lP0n2N","a0yWQOM5BD7bCvzgUC9xDd","a1/yw0fgJGC76BWc0YNJiB","a2MjXRFdtLlYQ5ouAFv/+R","a5IDozjpZI3J7MwRR/vHdv","aaxCsdJC1KIYBbbFKVDziQ","abLMj/XlhPMKE5Etu+j1ef","aceGtm2cRMK6yw40JImCI8","aciCCh5mlKr4mVGnrEGWKz","b3Tc7vqvtAEL7c/lwjMOQD","b3Xjnye/pO6Ixiet8Tv4Ks","b3wVuXl+tD3p+oKfdvm58m","b36r6oOGhIYbk3cmYU7WHr","b4YYyk5V9Mo493cWvGKmAO","b4vdhfCV1O94WujAz28nlA","b43I6fVoJIh5N5OFkjcHbf","b5TLorcHpNobgQbfn3ktOy","b5ZWlLhfNJX4EftV0MItsq","b5fMj3lYVOTo1kGW5+XuEF","b89yZL7xdMWKbF7Pzm1aJR","c2EM3XzyNHyaGPPBidqBfT","c23MtnVSZLerAj/pZtuLWw","c3CrWuqf1KEZDL8ZPcQUCx","c5zGERExpFmZ0Nws7cNQHB","c6Namnx85AxJV1X+uBUfd0","c6VQe753hGIIauRhPpDeqL","caE7WMvUlOnJQX13sWB2iW","ccsMq6Ax9FMLBc/jmZqAWd","cdAOxzpvFA3oQ8L1LamLtg","cdVRHJe/pPQ4HGeCfEbUlB","cdsQCVpnNDab/4qhp9Qv4T","d0GZM+fl1FM5D6zOfqS2z3","d2KiFhDhhNXrWlciJE5d5+","d2L7BaqvhIJ611VkmvREzZ","d2UF05wGFLo6d7qg6OFB2V","d4ll/DQvRDBr5ldld8ncFr","d7hXtrTOlJVoSul83HvCW0","d7y6fHlv1JaLuycKJi7nLH","d8VVozuz9JcpEKK7XJiYoR","d8f+Dra15HE6XsePzYGQla","db1Do2UD1OuIcjeYaKiJTC","ddClVdRCZOLrFGQLJAICXH","ddSZspdy1LFKGB7FnhHVDn","deFOggkABN7L6zhnkD4Xal","e0AP0n20NFNaGWduyxFwJo","e4tF4zSo5P85pxD9AIlnMJ","e7O7vpXT5M1oERec3/6O9S","e7h7lWfRBIgoSs6VzSJOtt","e7i7pZoNNKb7tlcVAEwgQ3","e8eKYHTghIhLbPQxcB+VTs","e9D8eg1NpGp64cz4/EeR7Q","e9yperpDZMZYivzXiW06bA","ea7kdikINAMYh/iKCWrVet","ebC2mTJu5He7Ma/GXqR7mI","ebkAd7eYZIOYrK7NnJU8GR","ecpdLyjvZBwrvm+cedCcQy","edSynQPnFCQro0i8Bwm8Al","eegKir6WpGGp+bh9CTdwH2","f0kpahWnVJla1WHJ/AKOGq","f0l4DsM7hFv7LVUqc5xYdR","f1GVLszPxIc4aceR3I4pCM","f1nMOfMZZPrrvS7JvNK3RM","f2WYM79ZJMfLwggmsr5n+j","fcDo9gjq1AB5X0xB3JdEH5","fcR6Oq6FVN36p5ggnxAXYk","fdl6sVn/5NgZMXCKkMdhHK","fe2gFtDXlBcIbP5Uo7/GD6","ffTYqaqSBMI6wo1WruqKso","ffjQoPGuBLDJSy/yLhRYSx"],"scenes":{},"redirect":[354,0,359,0,360,0,387,0,389,0,396,0,780,0,423,0,785,0,787,0,430,0,453,0,463,0,804,0,494,0,504,0,511,0,833,1,560,0,847,0,854,0,855,0,860,0,616,0,627,0,667,0,880,0,683,0,886,0,687,0,891,2,704,0,912,1,916,0,733,0,734,0],"deps":["Lobby","internal","main"],"packs":{"0123c5b44":[621,655],"0138b25c2":[459,725],"014b344c5":[401,425],"016bf6eb8":[376,741],"01cbfd1b0":[403,688],"0208ad676":[409,675],"02ef5db74":[508,639],"033c2f9f0":[349,353,756,384,395,400,402,404,411,426,454,466,110,483,484,121,488,495,499,500,502,506,538,550,557,576,580,608,644,676,299,319,728,730,731,736,738,920,743,744],"0491c4fbd":[370,598,603,729],"04b6572f9":[761,767,779,790,798,808,809,813,835,853,858,866,869,874,876,887,909,911],"054e0a170":[465,685],"05a23dc0c":[897,901],"05aa3d4c3":[372,487],"05f83005b":[513,702],"06016bde5":[749,758,764,774,775,781,783,784,803,807,810,812,815,816,820,829,832,841,843,844,861,623,865,872,884,888,892,894,895,915,918,921],"0625ca08e":[437,674],"068aaaa67":[0,1,2,3,4,5,6,7,8,9,10,11,12,13,14,15,16,17,18,19,20,21,22,23,24,25,26,27,28,29,30,31,32,33,34,35,36,37,38,39,40,41,42,43,44,45,46,47,48,49,50,393,51,52,53,54,55,56,57,58,59,60,62,63,66,67,68,69,70,71,72,73,75,76,77,78,79,80,81,82,84,86,87,88,89,90,91,92,93,94,95,97,98,99,100,101,102,103,104,105,107,108,109,111,112,113,114,115,116,117,118,119,120,122,123,124,125,126,127,128,129,130,131,132,133,134,135,136,137,138,139,140,141,142,143,144,145,147,148,149,150,151,152,153,154,155,156,157,158,159,160,161,162,163,164,165,166,167,168,169,170,171,172,173,174,175,176,177,178,179,180,181,182,183,184,185,186,187,188,189,190,567,191,192,193,194,195,196,197,198,199,200,201,202,203,204,205,206,208,209,210,211,212,213,214,215,216,217,218,219,220,221,222,223,224,225,226,227,228,229,230,231,232,233,234,235,236,237,238,239,240,241,242,243,244,245,246,247,248,249,250,251,252,253,255,256,257,258,259,260,261,262,263,264,265,266,267,268,269,270,271,272,273,274,275,276,277,278,279,280,281,282,283,284,285,286,287,288,289,290,291,292,293,294,295,296,297,298,300,301,302,303,304,305,306,307,308,309,311,312,313,314,315,316,317,318,321,322,323,324,325,327,328,329,330,331,332,333,334,335,336,337,338,339,340,343,344,345,346,347],"074d3d590":[420,626],"07d97f26e":[547,739],"07f47b75b":[541,548],"08288c091":[510,672],"08ba97786":[350,367,392,416,431,434,449,462,503,614,624,628,646,649,664,669,706,718,727],"090dc7863":[408,444,528,637],"0a09acfb1":[369,486],"0a7622063":[657,723],"0a82f94fd":[355,362,364,368,386,417,421,432,439,443,458,477,479,482,491,492,516,521,523,537,549,562,587,588,589,596,599,604,605,609,613,615,618,631,641,645,654,670,679,690,692,694,695,711,715,716],"0aa45a552":[375,565,570,678],"0b7b91b18":[415,478],"0c49438ac":[489,524],"0cae64865":[410,533],"0d4e16613":[747,751,768,769,782,789,797,805,817,819,824,828,542,834,846,868,875,878,879,889,893,899,902,903,910,917,919,922,925],"0d50787e9":[397,535],"0e088c3df":[748,750,752,753,754,757,762,763,765,766,391,770,772,773,776,778,786,788,791,792,793,794,795,796,800,801,802,806,811,814,818,822,823,825,826,827,830,831,836,837,838,840,842,845,848,851,852,856,857,859,862,863,864,867,870,871,873,881,882,883,890,896,898,900,904,905,906,907,908,913,914],"0e4b0acc2":[759,799,850,877,885,923,924],"0e9e88858":[418,433],"0ea64539c":[755,760,771,777,821,839,661],"0f1f8c961":[700,742],"0f2c4a3d9":[451,551],"0f53785e8":[413,467]},"name":"TaiXiuDouble","importBase":"import","nativeBase":"native","debug":false,"isZip":false,"encrypted":false,"versions":{"import":[348,"ab8ac","0123c5b44","b5aad","0138b25c2","ed6fb","014b344c5","cca94","016bf6eb8","4b139","01cbfd1b0","b7ad9","0208ad676","36b39",351,"f9fc4",352,"6ff9f","02ef5db74","da36a","033c2f9f0","443b9","0491c4fbd","161a0","04b6572f9","281a6","054e0a170","d1446","05a23dc0c","11338","05aa3d4c3","0bae8","05f83005b","c29e5","06016bde5","d28d3","0625ca08e","9bee3","068aaaa67","9957b",356,"663cf","074d3d590","253ec",357,"58526","07d97f26e","e9ca3","07f47b75b","f11a6","08288c091","bc3ce",358,"a07c2","08ba97786","6a74c",361,"07a42","090dc7863","c7fa3","0a09acfb1","74c59",363,"91c20","0a7622063","d5095","0a82f94fd","1848e","0aa45a552","43c14",365,"0e5de","0b7b91b18","e6b74",366,"15ede","0c49438ac","6f60c","0cae64865","e61c9","0d4e16613","8084b","0d50787e9","250d6","0e088c3df","7e3d3","0e4b0acc2","45d71","0e9e88858","df9b4","0ea64539c","93e37","0f1f8c961","86842",371,"38b59","0f2c4a3d9","fddeb","0f53785e8","82019",373,"16762",374,"7d30e",377,"e26bd",378,"97eb5",379,"4e470",380,"6110e",381,"9e6ea",382,"b9e85",383,"961b3",385,"363c2",388,"75c89",390,"a4690",394,"0d4b4",398,"07305",399,"ad27d",61,"daa2f",405,"5fc8d",406,"c60f0",407,"9ee4c",64,"81bb8",65,"c1948",412,"6e3f6",414,"4180a",419,"4b8d2",74,"969bf",422,"db79a",424,"c0099",83,"68074",427,"efc00",428,"bd380",85,"ec83b",429,"adbea",435,"2e808",436,"2f1b2",438,"baeda",96,"08689",440,"6e144",441,"53453",442,"e6df3",445,"894af",446,"9b776",447,"eea11",448,"19847",450,"e693c",452,"3088e",455,"d80f4",106,"bfcee",456,"5b230",457,"67f22",460,"80142",461,"7b50f",464,"60e2f",468,"f1c28",469,"ca59d",470,"0dabb",471,"dd3bb",472,"21ed1",473,"3e622",474,"a60f7",475,"9e922",476,"e55b8",480,"8b443",481,"bb88f",485,"e42a5",490,"0b6a4",493,"13ba0",496,"dbccd",497,"b47c9",498,"ba1be",501,"e001f",505,"78f63",507,"4e05e",509,"4bc54",512,"6e7b0",514,"9bd07",515,"82e0a",146,"daa2f",517,"e5703",518,"b947a",519,"00a07",520,"32bd9",522,"0614a",525,"3a8b3",526,"f4cbd",527,"2af2b",529,"ab96a",530,"dd4a1",531,"384b2",532,"d38ab",534,"e37d9",536,"69a1a",539,"38998",540,"a4ef5",543,"82551",544,"4dc80",545,"6b31b",546,"bc821",552,"712b7",553,"85b20",554,"8af33",555,"05bf6",556,"1c25c",558,"30292",559,"2cc67",561,"def9d",563,"456ea",564,"d6c83",566,"a627a",568,"9dbc4",569,"0d70f",571,"f1078",572,"80337",573,"aa2dd",574,"93653",575,"66832",577,"70f19",578,"afbbc",579,"054aa",581,"3dac4",582,"1e9d7",583,"19e30",584,"72f4d",585,"8a88a",586,"0f5f8",207,"969bf",590,"a4e8b",591,"ff7f1",849,"1ebe7",592,"777fd",593,"e1e9a",594,"3acd8",595,"8c822",597,"c1386",600,"51ead",601,"04d61",602,"b0572",606,"3ef03",607,"55b4a",610,"14a27",611,"880d9",612,"9736e",617,"13d32",619,"b7fd3",620,"995e4",622,"1d963",625,"96589",629,"6311d",630,"e4be5",632,"697e0",633,"0a86a",634,"df368",254,"969bf",635,"ee7ca",636,"693a8",638,"74658",640,"9a177",642,"aea47",643,"c9922",647,"e5657",648,"71910",650,"a02e7",651,"9ac63",652,"e4f13",653,"f1945",656,"ac145",658,"8a704",659,"c929f",660,"55513",662,"13125",663,"f9f2a",665,"e5105",666,"76e21",668,"44da7",671,"0167e",673,"f925e",677,"5e074",680,"69d3f",681,"c4aca",682,"c9bc2",684,"d4843",686,"3df49",689,"24c6d",691,"2f494",693,"76f5b",696,"863c5",697,"38ff3",698,"74941",699,"7b9e8",701,"8aef2",703,"7d7de",705,"f512a",707,"ade0e",708,"08151",709,"af89a",710,"6429f",310,"de652",712,"c46d1",713,"1e6b1",714,"7bb1d",717,"11ba4",719,"b0bc9",720,"dfb29",721,"73325",722,"af88e",320,"81bb8",724,"f5e8b",726,"8487b",326,"8d6d7",732,"37818",735,"bea14",737,"20d8e",740,"027b0",341,"969bf",342,"46495",745,"ba2fb",746,"03e76"],"native":[0,"61555",1,"2114a",2,"ff98b",3,"7d168",4,"8cd99",5,"68165",6,"41112",7,"0c711",8,"f7263",9,"82c0c",10,"04637",11,"26b10",12,"9dedb",13,"8c6b8",14,"55c3d",15,"55618",16,"696e2",17,"4a8f6",18,"8f385",19,"12611",20,"ead9b",21,"cacd7",22,"9cd1d",23,"4f609",24,"7a3c6",25,"0b1be",26,"02cf8",27,"74362",28,"01991",29,"2790e",30,"0e3a6",31,"c9448",32,"16c26",33,"aaced",34,"888c1",35,"38910",36,"f518a",37,"da17d",38,"ca98f",39,"57ff5",40,"88f8f",41,"25fd2",42,"62bda",43,"27bfa",44,"e4abf",45,"3c22c",46,"591af",47,"e2409",48,"7c131",49,"23857",50,"a7368",393,"5353b",51,"8edd6",52,"93dc8",53,"227eb",54,"91953",55,"27bfa",56,"bd8cf",57,"4db15",58,"3f373",59,"c3f8c",60,"57a56",61,"7ffc4",62,"9db6d",63,"15297",64,"adf59",65,"2e60f",66,"777b6",67,"5f7a7",68,"9e620",69,"0e3a6",70,"996ff",71,"0f770",72,"59489",73,"b75c5",74,"ed66f",75,"3c972",76,"7b954",77,"45975",78,"4383f",79,"b2e83",80,"d3732",81,"18fde",82,"aec42",83,"6d52a",84,"9ca76",85,"474a4",86,"04c81",87,"91d6d",88,"56c92",89,"f518a",90,"ac377",91,"03e8f",92,"c218c",93,"4492e",94,"f1e2d",95,"d9de9",96,"c2161",97,"b5e1c",98,"afcb0",99,"740b3",100,"6363b",101,"5e208",102,"df0fe",103,"57ff5",104,"c1cc3",105,"8afdb",106,"5a5d5",107,"96432",108,"1d1a0",109,"edc2f",110,"1c162",111,"535d8",112,"e594d",113,"46155",114,"32feb",115,"13a7e",116,"b1af0",117,"8c653",118,"740b3",119,"d7948",120,"197de",121,"b1b77",122,"fab72",123,"d949b",124,"759a8",125,"d2a2a",126,"0e2a2",127,"aca27",128,"2cd50",129,"cff19",130,"ea6e0",131,"bb1e8",132,"837f8",133,"90faf",134,"db1d6",135,"39103",136,"cf071",137,"b0fda",138,"0e3a6",139,"e594d",140,"74e78",141,"50b53",142,"0ed1d",143,"b4978",144,"b303f",145,"6c839",146,"7ffc4",147,"d890a",148,"76e17",149,"c807d",150,"e2984",151,"aa144",152,"30d67",153,"880a4",154,"f9a84",155,"cf845",156,"7837c",157,"9db6d",158,"9dedb",159,"e599f",160,"ccb8a",161,"db691",162,"cba01",163,"72d8c",164,"a05e6",165,"f518a",166,"e457e",167,"9e477",168,"6f650",169,"8c4b7",170,"a05e6",171,"b2889",172,"79275",173,"60abc",174,"7dbd0",175,"b1836",176,"591a1",177,"81a2b",178,"56819",179,"4e91c",180,"a54b7",181,"158e9",182,"5450c",183,"f3f97",184,"0bedd",185,"9abf8",186,"c85e9",187,"9227f",188,"c4689",189,"87071",190,"1fa9f",567,"55df1",191,"bba58",192,"fbe79",193,"7e98c",194,"263a8",195,"e5442",196,"f897c",197,"1f81a",198,"890e0",199,"3def6",200,"c9cd5",201,"275df",202,"b893b",203,"0261b",204,"8bf5e",205,"1fea1",206,"1f322",207,"634f9",208,"5c22c",209,"db9dd",210,"3163a",211,"30ccc",212,"28e18",213,"15783",214,"08cc2",215,"7bb22",216,"6b30a",217,"2f532",218,"ecb2a",219,"333c4",220,"68f6c",221,"84ca7",222,"9cb50",223,"ff98b",224,"88fe5",225,"0727f",226,"77d8d",227,"446dc",228,"19ff0",229,"1eaad",230,"3ad08",231,"11e7c",232,"b1af0",233,"93ca5",234,"2bee4",235,"fb2cb",236,"3e542",237,"b268b",238,"9e419",239,"ebe5b",240,"50a0a",241,"e7a0b",242,"6f650",243,"c2212",244,"9cd1d",245,"22535",246,"9e90e",247,"81689",248,"27143",249,"535d8",250,"a7fcc",251,"ce626",252,"162ed",253,"94fb9",254,"1da7a",255,"95d45",256,"2f7ef",257,"5d15e",258,"459a1",259,"d5ea1",260,"4b5db",261,"0c4e7",262,"08df1",263,"7b8f8",264,"06b9e",265,"4be0f",266,"6bf83",267,"b303f",268,"39326",269,"23857",270,"c16ba",271,"99b7f",272,"9b817",273,"d4418",274,"73e3a",275,"8ab8f",276,"7867f",277,"7546f",278,"bea72",279,"ffc4c",280,"b7596",281,"fb3ca",282,"2bee4",283,"d6ad7",284,"c1e0a",285,"c16ba",286,"847d4",287,"14155",288,"1d8e5",289,"e9682",290,"14491",291,"da17d",292,"95c26",293,"99fad",294,"0727f",295,"a7fcc",296,"0ed1d",297,"54a6b",298,"e60c4",299,"1b8cc",300,"08df1",301,"3be4e",302,"0ea88",303,"81a2b",304,"1bc53",305,"0e3a6",306,"c4689",307,"2d3a4",308,"4492e",309,"8ecea",310,"a75f6",311,"66fdb",312,"0c656",313,"1e8f5",314,"f4680",315,"e0b4b",316,"4c69e",317,"8acfc",318,"bfc15",319,"4c0e5",320,"adf59",321,"ab49a",322,"6c997",323,"4f21e",324,"e1db3",325,"d720c",326,"a8d6f",327,"d4356",328,"bfbe4",329,"fc844",330,"4021d",331,"ab890",332,"25fd2",333,"7ff95",334,"ed549",335,"3163a",336,"708a9",337,"71ff3",338,"583bd",339,"66b37",340,"ead9b",341,"634f9",342,"e709c",343,"90706",344,"face5",345,"edcf6",346,"98f93",347,"d1c3e"]}}